{"id":"feather_70","strokes":[{"id":"1", "points":[{"pid":"1", "time":1, "x":33.0000,"y":61.0574},{"pid":"2", "time":1, "x":33.0625,"y":61.0164},{"pid":"3", "time":1, "x":33.2432,"y":60.9014},{"pid":"4", "time":1, "x":33.5321,"y":60.7241},{"pid":"5", "time":1, "x":33.9194,"y":60.4965},{"pid":"6", "time":1, "x":34.3949,"y":60.2304},{"pid":"7", "time":1, "x":34.9487,"y":59.9376},{"pid":"8", "time":1, "x":35.5709,"y":59.6300},{"pid":"9", "time":1, "x":36.2514,"y":59.3195},{"pid":"10", "time":1, "x":36.9802,"y":59.0178},{"pid":"11", "time":1, "x":37.7474,"y":58.7369},{"pid":"12", "time":1, "x":38.5429,"y":58.4885},{"pid":"13", "time":1, "x":39.3569,"y":58.2846},{"pid":"14", "time":1, "x":40.1792,"y":58.1369},{"pid":"15", "time":1, "x":41.0000,"y":58.0574},{"pid":"16", "time":1, "x":41.0000,"y":58.0574},{"pid":"17", "time":1, "x":46.1484,"y":57.8334},{"pid":"18", "time":1, "x":51.3317,"y":57.6757},{"pid":"19", "time":1, "x":56.4834,"y":57.5763},{"pid":"20", "time":1, "x":61.5367,"y":57.5273},{"pid":"21", "time":1, "x":66.4250,"y":57.5206},{"pid":"22", "time":1, "x":71.0818,"y":57.5485},{"pid":"23", "time":1, "x":75.4402,"y":57.6028},{"pid":"24", "time":1, "x":79.4338,"y":57.6757},{"pid":"25", "time":1, "x":82.9958,"y":57.7592},{"pid":"26", "time":1, "x":86.0596,"y":57.8453},{"pid":"27", "time":1, "x":88.5585,"y":57.9262},{"pid":"28", "time":1, "x":90.4260,"y":57.9938},{"pid":"29", "time":1, "x":91.5954,"y":58.0401},{"pid":"30", "time":1, "x":92.0000,"y":58.0574},{"pid":"31", "time":1, "x":92.0000,"y":58.0574},{"pid":"32", "time":1, "x":92.0000,"y":58.0574},{"pid":"33", "time":1, "x":92.0000,"y":58.0574},{"pid":"34", "time":1, "x":92.0000,"y":58.0574},{"pid":"35", "time":1, "x":92.0000,"y":58.0574},{"pid":"36", "time":1, "x":92.0000,"y":58.0574},{"pid":"37", "time":1, "x":92.0000,"y":58.0574},{"pid":"38", "time":1, "x":92.0000,"y":58.0574},{"pid":"39", "time":1, "x":92.0000,"y":58.0574},{"pid":"40", "time":1, "x":92.0000,"y":58.0574},{"pid":"41", "time":1, "x":92.0000,"y":58.0574},{"pid":"42", "time":1, "x":92.0000,"y":58.0574},{"pid":"43", "time":1, "x":92.0000,"y":58.0574},{"pid":"44", "time":1, "x":92.0000,"y":58.0574},{"pid":"45", "time":1, "x":92.0000,"y":58.0574}]},{"id":"2", "points":[{"pid":"1", "time":1, "x":92.0000,"y":60.0574},{"pid":"2", "time":1, "x":91.9286,"y":59.9859},{"pid":"3", "time":1, "x":91.8571,"y":59.9145},{"pid":"4", "time":1, "x":91.7857,"y":59.8431},{"pid":"5", "time":1, "x":91.7143,"y":59.7717},{"pid":"6", "time":1, "x":91.6429,"y":59.7002},{"pid":"7", "time":1, "x":91.5714,"y":59.6288},{"pid":"8", "time":1, "x":91.5000,"y":59.5574},{"pid":"9", "time":1, "x":91.4286,"y":59.4859},{"pid":"10", "time":1, "x":91.3571,"y":59.4145},{"pid":"11", "time":1, "x":91.2857,"y":59.3431},{"pid":"12", "time":1, "x":91.2143,"y":59.2717},{"pid":"13", "time":1, "x":91.1429,"y":59.2002},{"pid":"14", "time":1, "x":91.0714,"y":59.1288},{"pid":"15", "time":1, "x":91.0000,"y":59.0574}]},{"id":"3", "points":[{"pid":"1", "time":1, "x":95.0000,"y":58.0574},{"pid":"2", "time":1, "x":95.0015,"y":58.1369},{"pid":"3", "time":1, "x":95.0085,"y":58.3651},{"pid":"4", "time":1, "x":95.0253,"y":58.7264},{"pid":"5", "time":1, "x":95.0557,"y":59.2055},{"pid":"6", "time":1, "x":95.1039,"y":59.7867},{"pid":"7", "time":1, "x":95.1737,"y":60.4546},{"pid":"8", "time":1, "x":95.2694,"y":61.1936},{"pid":"9", "time":1, "x":95.3949,"y":61.9883},{"pid":"10", "time":1, "x":95.5543,"y":62.8232},{"pid":"11", "time":1, "x":95.7515,"y":63.6827},{"pid":"12", "time":1, "x":95.9907,"y":64.5514},{"pid":"13", "time":1, "x":96.2758,"y":65.4137},{"pid":"14", "time":1, "x":96.6109,"y":66.2542},{"pid":"15", "time":1, "x":97.0000,"y":67.0574},{"pid":"16", "time":1, "x":97.0000,"y":67.0574},{"pid":"17", "time":1, "x":98.0066,"y":68.9783},{"pid":"18", "time":1, "x":98.8921,"y":70.7358},{"pid":"19", "time":1, "x":99.6837,"y":72.3491},{"pid":"20", "time":1, "x":100.4088,"y":73.8373},{"pid":"21", "time":1, "x":101.0946,"y":75.2196},{"pid":"22", "time":1, "x":101.7684,"y":76.5152},{"pid":"23", "time":1, "x":102.4574,"y":77.7432},{"pid":"24", "time":1, "x":103.1890,"y":78.9228},{"pid":"25", "time":1, "x":103.9905,"y":80.0732},{"pid":"26", "time":1, "x":104.8890,"y":81.2135},{"pid":"27", "time":1, "x":105.9120,"y":82.3629},{"pid":"28", "time":1, "x":107.0866,"y":83.5405},{"pid":"29", "time":1, "x":108.4402,"y":84.7656},{"pid":"30", "time":1, "x":110.0000,"y":86.0574},{"pid":"31", "time":1, "x":110.0000,"y":86.0574},{"pid":"32", "time":1, "x":113.3999,"y":88.7123},{"pid":"33", "time":1, "x":116.4927,"y":91.0204},{"pid":"34", "time":1, "x":119.3370,"y":93.0321},{"pid":"35", "time":1, "x":121.9915,"y":94.7981},{"pid":"36", "time":1, "x":124.5148,"y":96.3688},{"pid":"37", "time":1, "x":126.9656,"y":97.7949},{"pid":"38", "time":1, "x":129.4025,"y":99.1267},{"pid":"39", "time":1, "x":131.8843,"y":100.4149},{"pid":"40", "time":1, "x":134.4694,"y":101.7100},{"pid":"41", "time":1, "x":137.2167,"y":103.0625},{"pid":"42", "time":1, "x":140.1848,"y":104.5230},{"pid":"43", "time":1, "x":143.4322,"y":106.1419},{"pid":"44", "time":1, "x":147.0178,"y":107.9699},{"pid":"45", "time":1, "x":151.0000,"y":110.0574},{"pid":"46", "time":1, "x":151.0000,"y":110.0574},{"pid":"47", "time":1, "x":151.4851,"y":110.3051},{"pid":"48", "time":1, "x":151.9260,"y":110.5083},{"pid":"49", "time":1, "x":152.3315,"y":110.6714},{"pid":"50", "time":1, "x":152.7104,"y":110.7987},{"pid":"51", "time":1, "x":153.0718,"y":110.8945},{"pid":"52", "time":1, "x":153.4244,"y":110.9632},{"pid":"53", "time":1, "x":153.7773,"y":111.0091},{"pid":"54", "time":1, "x":154.1392,"y":111.0366},{"pid":"55", "time":1, "x":154.5192,"y":111.0499},{"pid":"56", "time":1, "x":154.9260,"y":111.0536},{"pid":"57", "time":1, "x":155.3686,"y":111.0518},{"pid":"58", "time":1, "x":155.8558,"y":111.0489},{"pid":"59", "time":1, "x":156.3967,"y":111.0493},{"pid":"60", "time":1, "x":157.0000,"y":111.0574},{"pid":"61", "time":1, "x":157.0000,"y":111.0574},{"pid":"62", "time":1, "x":171.1108,"y":111.3563},{"pid":"63", "time":1, "x":184.2607,"y":111.6422},{"pid":"64", "time":1, "x":196.5264,"y":111.9124},{"pid":"65", "time":1, "x":207.9845,"y":112.1640},{"pid":"66", "time":1, "x":218.7115,"y":112.3943},{"pid":"67", "time":1, "x":228.7841,"y":112.6007},{"pid":"68", "time":1, "x":238.2790,"y":112.7803},{"pid":"69", "time":1, "x":247.2726,"y":112.9304},{"pid":"70", "time":1, "x":255.8417,"y":113.0482},{"pid":"71", "time":1, "x":264.0628,"y":113.1310},{"pid":"72", "time":1, "x":272.0126,"y":113.1761},{"pid":"73", "time":1, "x":279.7676,"y":113.1807},{"pid":"74", "time":1, "x":287.4046,"y":113.1420},{"pid":"75", "time":1, "x":295.0000,"y":113.0574},{"pid":"76", "time":1, "x":295.0000,"y":113.0574},{"pid":"77", "time":1, "x":295.1190,"y":112.9979},{"pid":"78", "time":1, "x":295.2481,"y":112.8343},{"pid":"79", "time":1, "x":295.3859,"y":112.5839},{"pid":"80", "time":1, "x":295.5306,"y":112.2640},{"pid":"81", "time":1, "x":295.6806,"y":111.8920},{"pid":"82", "time":1, "x":295.8343,"y":111.4852},{"pid":"83", "time":1, "x":295.9901,"y":111.0609},{"pid":"84", "time":1, "x":296.1462,"y":110.6365},{"pid":"85", "time":1, "x":296.3011,"y":110.2293},{"pid":"86", "time":1, "x":296.4532,"y":109.8565},{"pid":"87", "time":1, "x":296.6007,"y":109.5356},{"pid":"88", "time":1, "x":296.7421,"y":109.2839},{"pid":"89", "time":1, "x":296.8758,"y":109.1187},{"pid":"90", "time":1, "x":297.0000,"y":109.0574},{"pid":"91", "time":1, "x":297.0000,"y":109.0574},{"pid":"92", "time":1, "x":304.1491,"y":108.8971},{"pid":"93", "time":1, "x":311.2991,"y":108.8441},{"pid":"94", "time":1, "x":318.5265,"y":108.8777},{"pid":"95", "time":1, "x":325.9078,"y":108.9772},{"pid":"96", "time":1, "x":333.5193,"y":109.1220},{"pid":"97", "time":1, "x":341.4376,"y":109.2915},{"pid":"98", "time":1, "x":349.7391,"y":109.4649},{"pid":"99", "time":1, "x":358.5001,"y":109.6218},{"pid":"100", "time":1, "x":367.7973,"y":109.7413},{"pid":"101", "time":1, "x":377.7070,"y":109.8029},{"pid":"102", "time":1, "x":388.3057,"y":109.7860},{"pid":"103", "time":1, "x":399.6698,"y":109.6699},{"pid":"104", "time":1, "x":411.8757,"y":109.4339},{"pid":"105", "time":1, "x":425.0000,"y":109.0574},{"pid":"106", "time":1, "x":425.0000,"y":109.0574},{"pid":"107", "time":1, "x":430.1751,"y":108.8337},{"pid":"108", "time":1, "x":434.6755,"y":108.5391},{"pid":"109", "time":1, "x":438.6138,"y":108.1835},{"pid":"110", "time":1, "x":442.1023,"y":107.7766},{"pid":"111", "time":1, "x":445.2537,"y":107.3285},{"pid":"112", "time":1, "x":448.1803,"y":106.8488},{"pid":"113", "time":1, "x":450.9946,"y":106.3474},{"pid":"114", "time":1, "x":453.8092,"y":105.8342},{"pid":"115", "time":1, "x":456.7365,"y":105.3190},{"pid":"116", "time":1, "x":459.8889,"y":104.8116},{"pid":"117", "time":1, "x":463.3790,"y":104.3219},{"pid":"118", "time":1, "x":467.3192,"y":103.8598},{"pid":"119", "time":1, "x":471.8221,"y":103.4350},{"pid":"120", "time":1, "x":477.0000,"y":103.0574},{"pid":"121", "time":1, "x":477.0000,"y":103.0574},{"pid":"122", "time":1, "x":481.2739,"y":102.8522},{"pid":"123", "time":1, "x":485.0334,"y":102.7933},{"pid":"124", "time":1, "x":488.3607,"y":102.8522},{"pid":"125", "time":1, "x":491.3383,"y":102.9999},{"pid":"126", "time":1, "x":494.0485,"y":103.2079},{"pid":"127", "time":1, "x":496.5736,"y":103.4475},{"pid":"128", "time":1, "x":498.9962,"y":103.6900},{"pid":"129", "time":1, "x":501.3985,"y":103.9066},{"pid":"130", "time":1, "x":503.8629,"y":104.0687},{"pid":"131", "time":1, "x":506.4719,"y":104.1476},{"pid":"132", "time":1, "x":509.3077,"y":104.1146},{"pid":"133", "time":1, "x":512.4527,"y":103.9411},{"pid":"134", "time":1, "x":515.9893,"y":103.5982},{"pid":"135", "time":1, "x":520.0000,"y":103.0574},{"pid":"136", "time":1, "x":520.0000,"y":103.0574},{"pid":"137", "time":1, "x":523.5291,"y":102.4975},{"pid":"138", "time":1, "x":526.6405,"y":101.9503},{"pid":"139", "time":1, "x":529.4020,"y":101.4014},{"pid":"140", "time":1, "x":531.8810,"y":100.8360},{"pid":"141", "time":1, "x":534.1450,"y":100.2395},{"pid":"142", "time":1, "x":536.2618,"y":99.5973},{"pid":"143", "time":1, "x":538.2988,"y":98.8948},{"pid":"144", "time":1, "x":540.3236,"y":98.1172},{"pid":"145", "time":1, "x":542.4037,"y":97.2500},{"pid":"146", "time":1, "x":544.6068,"y":96.2785},{"pid":"147", "time":1, "x":547.0004,"y":95.1882},{"pid":"148", "time":1, "x":549.6521,"y":93.9643},{"pid":"149", "time":1, "x":552.6295,"y":92.5922},{"pid":"150", "time":1, "x":556.0000,"y":91.0574},{"pid":"151", "time":1, "x":556.0000,"y":91.0574},{"pid":"152", "time":1, "x":558.8619,"y":89.7028},{"pid":"153", "time":1, "x":561.6714,"y":88.2602},{"pid":"154", "time":1, "x":564.4030,"y":86.7597},{"pid":"155", "time":1, "x":567.0312,"y":85.2314},{"pid":"156", "time":1, "x":569.5303,"y":83.7055},{"pid":"157", "time":1, "x":571.8748,"y":82.2122},{"pid":"158", "time":1, "x":574.0392,"y":80.7816},{"pid":"159", "time":1, "x":575.9979,"y":79.4439},{"pid":"160", "time":1, "x":577.7254,"y":78.2292},{"pid":"161", "time":1, "x":579.1961,"y":77.1678},{"pid":"162", "time":1, "x":580.3845,"y":76.2897},{"pid":"163", "time":1, "x":581.2650,"y":75.6252},{"pid":"164", "time":1, "x":581.8120,"y":75.2044},{"pid":"165", "time":1, "x":582.0000,"y":75.0574},{"pid":"166", "time":1, "x":582.0000,"y":75.0574},{"pid":"167", "time":1, "x":582.0000,"y":75.0574},{"pid":"168", "time":1, "x":582.0000,"y":75.0574},{"pid":"169", "time":1, "x":582.0000,"y":75.0574},{"pid":"170", "time":1, "x":582.0000,"y":75.0574},{"pid":"171", "time":1, "x":582.0000,"y":75.0574},{"pid":"172", "time":1, "x":582.0000,"y":75.0574},{"pid":"173", "time":1, "x":582.0000,"y":75.0574},{"pid":"174", "time":1, "x":582.0000,"y":75.0574},{"pid":"175", "time":1, "x":582.0000,"y":75.0574},{"pid":"176", "time":1, "x":582.0000,"y":75.0574},{"pid":"177", "time":1, "x":582.0000,"y":75.0574},{"pid":"178", "time":1, "x":582.0000,"y":75.0574},{"pid":"179", "time":1, "x":582.0000,"y":75.0574},{"pid":"180", "time":1, "x":582.0000,"y":75.0574}]},{"id":"4", "points":[{"pid":"1", "time":1, "x":95.0000,"y":58.0574},{"pid":"2", "time":1, "x":94.9994,"y":57.8827},{"pid":"3", "time":1, "x":95.0025,"y":57.3827},{"pid":"4", "time":1, "x":95.0165,"y":56.5932},{"pid":"5", "time":1, "x":95.0490,"y":55.5500},{"pid":"6", "time":1, "x":95.1072,"y":54.2891},{"pid":"7", "time":1, "x":95.1984,"y":52.8462},{"pid":"8", "time":1, "x":95.3300,"y":51.2573},{"pid":"9", "time":1, "x":95.5094,"y":49.5582},{"pid":"10", "time":1, "x":95.7439,"y":47.7847},{"pid":"11", "time":1, "x":96.0409,"y":45.9727},{"pid":"12", "time":1, "x":96.4076,"y":44.1582},{"pid":"13", "time":1, "x":96.8515,"y":42.3768},{"pid":"14", "time":1, "x":97.3798,"y":40.6646},{"pid":"15", "time":1, "x":98.0000,"y":39.0574},{"pid":"16", "time":1, "x":98.0000,"y":39.0574},{"pid":"17", "time":1, "x":98.5013,"y":37.9388},{"pid":"18", "time":1, "x":99.0009,"y":36.9078},{"pid":"19", "time":1, "x":99.5075,"y":35.9552},{"pid":"20", "time":1, "x":100.0297,"y":35.0720},{"pid":"21", "time":1, "x":100.5760,"y":34.2491},{"pid":"22", "time":1, "x":101.1551,"y":33.4774},{"pid":"23", "time":1, "x":101.7755,"y":32.7478},{"pid":"24", "time":1, "x":102.4459,"y":32.0512},{"pid":"25", "time":1, "x":103.1750,"y":31.3787},{"pid":"26", "time":1, "x":103.9712,"y":30.7210},{"pid":"27", "time":1, "x":104.8432,"y":30.0691},{"pid":"28", "time":1, "x":105.7996,"y":29.4139},{"pid":"29", "time":1, "x":106.8490,"y":28.7464},{"pid":"30", "time":1, "x":108.0000,"y":28.0574},{"pid":"31", "time":1, "x":108.0000,"y":28.0574},{"pid":"32", "time":1, "x":111.3196,"y":26.1011},{"pid":"33", "time":1, "x":114.2888,"y":24.3237},{"pid":"34", "time":1, "x":116.9719,"y":22.7091},{"pid":"35", "time":1, "x":119.4333,"y":21.2409},{"pid":"36", "time":1, "x":121.7372,"y":19.9031},{"pid":"37", "time":1, "x":123.9481,"y":18.6795},{"pid":"38", "time":1, "x":126.1301,"y":17.5538},{"pid":"39", "time":1, "x":128.3476,"y":16.5099},{"pid":"40", "time":1, "x":130.6649,"y":15.5316},{"pid":"41", "time":1, "x":133.1464,"y":14.6027},{"pid":"42", "time":1, "x":135.8563,"y":13.7070},{"pid":"43", "time":1, "x":138.8590,"y":12.8284},{"pid":"44", "time":1, "x":142.2188,"y":11.9505},{"pid":"45", "time":1, "x":146.0000,"y":11.0574},{"pid":"46", "time":1, "x":146.0000,"y":11.0574},{"pid":"47", "time":1, "x":151.3138,"y":9.9692},{"pid":"48", "time":1, "x":156.5139,"y":9.1090},{"pid":"49", "time":1, "x":161.5754,"y":8.4507},{"pid":"50", "time":1, "x":166.4735,"y":7.9681},{"pid":"51", "time":1, "x":171.1833,"y":7.6351},{"pid":"52", "time":1, "x":175.6800,"y":7.4255},{"pid":"53", "time":1, "x":179.9388,"y":7.3132},{"pid":"54", "time":1, "x":183.9347,"y":7.2722},{"pid":"55", "time":1, "x":187.6430,"y":7.2762},{"pid":"56", "time":1, "x":191.0388,"y":7.2991},{"pid":"57", "time":1, "x":194.0972,"y":7.3148},{"pid":"58", "time":1, "x":196.7935,"y":7.2972},{"pid":"59", "time":1, "x":199.1027,"y":7.2201},{"pid":"60", "time":1, "x":201.0000,"y":7.0574},{"pid":"61", "time":1, "x":201.0000,"y":7.0574},{"pid":"62", "time":1, "x":201.0066,"y":7.0142},{"pid":"63", "time":1, "x":201.0046,"y":6.8959},{"pid":"64", "time":1, "x":200.9959,"y":6.7146},{"pid":"65", "time":1, "x":200.9824,"y":6.4825},{"pid":"66", "time":1, "x":200.9659,"y":6.2119},{"pid":"67", "time":1, "x":200.9484,"y":5.9150},{"pid":"68", "time":1, "x":200.9318,"y":5.6039},{"pid":"69", "time":1, "x":200.9180,"y":5.2910},{"pid":"70", "time":1, "x":200.9089,"y":4.9883},{"pid":"71", "time":1, "x":200.9063,"y":4.7082},{"pid":"72", "time":1, "x":200.9123,"y":4.4628},{"pid":"73", "time":1, "x":200.9286,"y":4.2644},{"pid":"74", "time":1, "x":200.9572,"y":4.1252},{"pid":"75", "time":1, "x":201.0000,"y":4.0574},{"pid":"76", "time":1, "x":201.0000,"y":4.0574},{"pid":"77", "time":1, "x":201.3331,"y":3.8822},{"pid":"78", "time":1, "x":201.7185,"y":3.6995},{"pid":"79", "time":1, "x":202.1551,"y":3.5123},{"pid":"80", "time":1, "x":202.6417,"y":3.3238},{"pid":"81", "time":1, "x":203.1772,"y":3.1370},{"pid":"82", "time":1, "x":203.7603,"y":2.9553},{"pid":"83", "time":1, "x":204.3899,"y":2.7816},{"pid":"84", "time":1, "x":205.0648,"y":2.6192},{"pid":"85", "time":1, "x":205.7839,"y":2.4713},{"pid":"86", "time":1, "x":206.5459,"y":2.3408},{"pid":"87", "time":1, "x":207.3497,"y":2.2311},{"pid":"88", "time":1, "x":208.1941,"y":2.1451},{"pid":"89", "time":1, "x":209.0779,"y":2.0862},{"pid":"90", "time":1, "x":210.0000,"y":2.0574},{"pid":"91", "time":1, "x":210.0000,"y":2.0574},{"pid":"92", "time":1, "x":216.3272,"y":2.0010},{"pid":"93", "time":1, "x":221.8531,"y":2.0078},{"pid":"94", "time":1, "x":226.7132,"y":2.0669},{"pid":"95", "time":1, "x":231.0431,"y":2.1674},{"pid":"96", "time":1, "x":234.9783,"y":2.2984},{"pid":"97", "time":1, "x":238.6543,"y":2.4490},{"pid":"98", "time":1, "x":242.2068,"y":2.6084},{"pid":"99", "time":1, "x":245.7712,"y":2.7658},{"pid":"100", "time":1, "x":249.4832,"y":2.9102},{"pid":"101", "time":1, "x":253.4782,"y":3.0308},{"pid":"102", "time":1, "x":257.8919,"y":3.1166},{"pid":"103", "time":1, "x":262.8597,"y":3.1569},{"pid":"104", "time":1, "x":268.5172,"y":3.1408},{"pid":"105", "time":1, "x":275.0000,"y":3.0574},{"pid":"106", "time":1, "x":275.0000,"y":3.0574},{"pid":"107", "time":1, "x":279.9856,"y":2.9443},{"pid":"108", "time":1, "x":284.3223,"y":2.7947},{"pid":"109", "time":1, "x":288.1179,"y":2.6136},{"pid":"110", "time":1, "x":291.4804,"y":2.4065},{"pid":"111", "time":1, "x":294.5175,"y":2.1785},{"pid":"112", "time":1, "x":297.3370,"y":1.9349},{"pid":"113", "time":1, "x":300.0468,"y":1.6811},{"pid":"114", "time":1, "x":302.7547,"y":1.4222},{"pid":"115", "time":1, "x":305.5685,"y":1.1635},{"pid":"116", "time":1, "x":308.5960,"y":0.9102},{"pid":"117", "time":1, "x":311.9451,"y":0.6678},{"pid":"118", "time":1, "x":315.7236,"y":0.4413},{"pid":"119", "time":1, "x":320.0393,"y":0.2361},{"pid":"120", "time":1, "x":325.0000,"y":0.0574},{"pid":"121", "time":1, "x":325.0000,"y":0.0574},{"pid":"122", "time":1, "x":326.5301,"y":0.0187},{"pid":"123", "time":1, "x":327.9484,"y":0.0000},{"pid":"124", "time":1, "x":329.2650,"y":0.0005},{"pid":"125", "time":1, "x":330.4904,"y":0.0195},{"pid":"126", "time":1, "x":331.6349,"y":0.0561},{"pid":"127", "time":1, "x":332.7088,"y":0.1097},{"pid":"128", "time":1, "x":333.7225,"y":0.1794},{"pid":"129", "time":1, "x":334.6863,"y":0.2646},{"pid":"130", "time":1, "x":335.6105,"y":0.3645},{"pid":"131", "time":1, "x":336.5055,"y":0.4783},{"pid":"132", "time":1, "x":337.3816,"y":0.6052},{"pid":"133", "time":1, "x":338.2492,"y":0.7445},{"pid":"134", "time":1, "x":339.1185,"y":0.8955},{"pid":"135", "time":1, "x":340.0000,"y":1.0574},{"pid":"136", "time":1, "x":340.0000,"y":1.0574},{"pid":"137", "time":1, "x":340.0801,"y":1.0994},{"pid":"138", "time":1, "x":340.1590,"y":1.1899},{"pid":"139", "time":1, "x":340.2367,"y":1.3205},{"pid":"140", "time":1, "x":340.3132,"y":1.4830},{"pid":"141", "time":1, "x":340.3884,"y":1.6693},{"pid":"142", "time":1, "x":340.4622,"y":1.8711},{"pid":"143", "time":1, "x":340.5347,"y":2.0801},{"pid":"144", "time":1, "x":340.6058,"y":2.2883},{"pid":"145", "time":1, "x":340.6754,"y":2.4873},{"pid":"146", "time":1, "x":340.7435,"y":2.6689},{"pid":"147", "time":1, "x":340.8100,"y":2.8249},{"pid":"148", "time":1, "x":340.8750,"y":2.9472},{"pid":"149", "time":1, "x":340.9383,"y":3.0274},{"pid":"150", "time":1, "x":341.0000,"y":3.0574},{"pid":"151", "time":1, "x":341.0000,"y":3.0574},{"pid":"152", "time":1, "x":345.9635,"y":3.1972},{"pid":"153", "time":1, "x":351.1734,"y":3.2861},{"pid":"154", "time":1, "x":356.6106,"y":3.3342},{"pid":"155", "time":1, "x":362.2561,"y":3.3515},{"pid":"156", "time":1, "x":368.0911,"y":3.3483},{"pid":"157", "time":1, "x":374.0965,"y":3.3346},{"pid":"158", "time":1, "x":380.2534,"y":3.3204},{"pid":"159", "time":1, "x":386.5429,"y":3.3159},{"pid":"160", "time":1, "x":392.9458,"y":3.3311},{"pid":"161", "time":1, "x":399.4434,"y":3.3763},{"pid":"162", "time":1, "x":406.0165,"y":3.4614},{"pid":"163", "time":1, "x":412.6463,"y":3.5965},{"pid":"164", "time":1, "x":419.3138,"y":3.7918},{"pid":"165", "time":1, "x":426.0000,"y":4.0574},{"pid":"166", "time":1, "x":426.0000,"y":4.0574},{"pid":"167", "time":1, "x":426.2396,"y":4.1091},{"pid":"168", "time":1, "x":426.4663,"y":4.2340},{"pid":"169", "time":1, "x":426.6826,"y":4.4199},{"pid":"170", "time":1, "x":426.8905,"y":4.6549},{"pid":"171", "time":1, "x":427.0923,"y":4.9269},{"pid":"172", "time":1, "x":427.2902,"y":5.2239},{"pid":"173", "time":1, "x":427.4864,"y":5.5339},{"pid":"174", "time":1, "x":427.6832,"y":5.8448},{"pid":"175", "time":1, "x":427.8827,"y":6.1447},{"pid":"176", "time":1, "x":428.0873,"y":6.4215},{"pid":"177", "time":1, "x":428.2991,"y":6.6632},{"pid":"178", "time":1, "x":428.5203,"y":6.8578},{"pid":"179", "time":1, "x":428.7532,"y":6.9932},{"pid":"180", "time":1, "x":429.0000,"y":7.0574},{"pid":"181", "time":1, "x":429.0000,"y":7.0574},{"pid":"182", "time":1, "x":431.0895,"y":7.2138},{"pid":"183", "time":1, "x":433.0470,"y":7.2758},{"pid":"184", "time":1, "x":434.9020,"y":7.2610},{"pid":"185", "time":1, "x":436.6841,"y":7.1868},{"pid":"186", "time":1, "x":438.4229,"y":7.0711},{"pid":"187", "time":1, "x":440.1480,"y":6.9312},{"pid":"188", "time":1, "x":441.8888,"y":6.7849},{"pid":"189", "time":1, "x":443.6749,"y":6.6496},{"pid":"190", "time":1, "x":445.5360,"y":6.5432},{"pid":"191", "time":1, "x":447.5016,"y":6.4830},{"pid":"192", "time":1, "x":449.6012,"y":6.4867},{"pid":"193", "time":1, "x":451.8644,"y":6.5720},{"pid":"194", "time":1, "x":454.3209,"y":6.7563},{"pid":"195", "time":1, "x":457.0000,"y":7.0574},{"pid":"196", "time":1, "x":457.0000,"y":7.0574},{"pid":"197", "time":1, "x":458.7547,"y":7.3329},{"pid":"198", "time":1, "x":460.2868,"y":7.6642},{"pid":"199", "time":1, "x":461.6340,"y":8.0432},{"pid":"200", "time":1, "x":462.8338,"y":8.4617},{"pid":"201", "time":1, "x":463.9238,"y":8.9119},{"pid":"202", "time":1, "x":464.9417,"y":9.3856},{"pid":"203", "time":1, "x":465.9251,"y":9.8748},{"pid":"204", "time":1, "x":466.9115,"y":10.3715},{"pid":"205", "time":1, "x":467.9386,"y":10.8675},{"pid":"206", "time":1, "x":469.0439,"y":11.3550},{"pid":"207", "time":1, "x":470.2651,"y":11.8257},{"pid":"208", "time":1, "x":471.6398,"y":12.2717},{"pid":"209", "time":1, "x":473.2055,"y":12.6850},{"pid":"210", "time":1, "x":475.0000,"y":13.0574},{"pid":"211", "time":1, "x":475.0000,"y":13.0574},{"pid":"212", "time":1, "x":477.5021,"y":13.4562},{"pid":"213", "time":1, "x":479.7309,"y":13.7063},{"pid":"214", "time":1, "x":481.7299,"y":13.8349},{"pid":"215", "time":1, "x":483.5426,"y":13.8694},{"pid":"216", "time":1, "x":485.2126,"y":13.8372},{"pid":"217", "time":1, "x":486.7833,"y":13.7656},{"pid":"218", "time":1, "x":488.2984,"y":13.6820},{"pid":"219", "time":1, "x":489.8013,"y":13.6136},{"pid":"220", "time":1, "x":491.3355,"y":13.5880},{"pid":"221", "time":1, "x":492.9446,"y":13.6324},{"pid":"222", "time":1, "x":494.6720,"y":13.7742},{"pid":"223", "time":1, "x":496.5614,"y":14.0407},{"pid":"224", "time":1, "x":498.6562,"y":14.4593},{"pid":"225", "time":1, "x":501.0000,"y":15.0574},{"pid":"226", "time":1, "x":501.0000,"y":15.0574},{"pid":"227", "time":1, "x":504.0458,"y":15.9736},{"pid":"228", "time":1, "x":506.6974,"y":16.8911},{"pid":"229", "time":1, "x":509.0216,"y":17.8129},{"pid":"230", "time":1, "x":511.0848,"y":18.7418},{"pid":"231", "time":1, "x":512.9535,"y":19.6807},{"pid":"232", "time":1, "x":514.6943,"y":20.6324},{"pid":"233", "time":1, "x":516.3737,"y":21.6000},{"pid":"234", "time":1, "x":518.0582,"y":22.5863},{"pid":"235", "time":1, "x":519.8145,"y":23.5941},{"pid":"236", "time":1, "x":521.7090,"y":24.6263},{"pid":"237", "time":1, "x":523.8082,"y":25.6859},{"pid":"238", "time":1, "x":526.1788,"y":26.7756},{"pid":"239", "time":1, "x":528.8872,"y":27.8985},{"pid":"240", "time":1, "x":532.0000,"y":29.0574},{"pid":"241", "time":1, "x":532.0000,"y":29.0574},{"pid":"242", "time":1, "x":533.8893,"y":29.6635},{"pid":"243", "time":1, "x":535.5990,"y":30.0990},{"pid":"244", "time":1, "x":537.1563,"y":30.3940},{"pid":"245", "time":1, "x":538.5885,"y":30.5790},{"pid":"246", "time":1, "x":539.9226,"y":30.6843},{"pid":"247", "time":1, "x":541.1858,"y":30.7403},{"pid":"248", "time":1, "x":542.4053,"y":30.7774},{"pid":"249", "time":1, "x":543.6083,"y":30.8259},{"pid":"250", "time":1, "x":544.8219,"y":30.9162},{"pid":"251", "time":1, "x":546.0732,"y":31.0787},{"pid":"252", "time":1, "x":547.3896,"y":31.3437},{"pid":"253", "time":1, "x":548.7980,"y":31.7415},{"pid":"254", "time":1, "x":550.3258,"y":32.3026},{"pid":"255", "time":1, "x":552.0000,"y":33.0574},{"pid":"256", "time":1, "x":552.0000,"y":33.0574},{"pid":"257", "time":1, "x":555.3594,"y":34.7103},{"pid":"258", "time":1, "x":558.4515,"y":36.2495},{"pid":"259", "time":1, "x":561.3047,"y":37.7004},{"pid":"260", "time":1, "x":563.9471,"y":39.0882},{"pid":"261", "time":1, "x":566.4071,"y":40.4382},{"pid":"262", "time":1, "x":568.7129,"y":41.7756},{"pid":"263", "time":1, "x":570.8928,"y":43.1258},{"pid":"264", "time":1, "x":572.9750,"y":44.5140},{"pid":"265", "time":1, "x":574.9878,"y":45.9655},{"pid":"266", "time":1, "x":576.9595,"y":47.5056},{"pid":"267", "time":1, "x":578.9183,"y":49.1595},{"pid":"268", "time":1, "x":580.8925,"y":50.9526},{"pid":"269", "time":1, "x":582.9103,"y":52.9101},{"pid":"270", "time":1, "x":585.0000,"y":55.0574},{"pid":"271", "time":1, "x":585.0000,"y":55.0574},{"pid":"272", "time":1, "x":585.7890,"y":56.0119},{"pid":"273", "time":1, "x":586.4918,"y":57.1035},{"pid":"274", "time":1, "x":587.1105,"y":58.3079},{"pid":"275", "time":1, "x":587.6474,"y":59.6007},{"pid":"276", "time":1, "x":588.1047,"y":60.9579},{"pid":"277", "time":1, "x":588.4845,"y":62.3549},{"pid":"278", "time":1, "x":588.7890,"y":63.7677},{"pid":"279", "time":1, "x":589.0206,"y":65.1719},{"pid":"280", "time":1, "x":589.1814,"y":66.5432},{"pid":"281", "time":1, "x":589.2735,"y":67.8574},{"pid":"282", "time":1, "x":589.2992,"y":69.0902},{"pid":"283", "time":1, "x":589.2607,"y":70.2173},{"pid":"284", "time":1, "x":589.1603,"y":71.2145},{"pid":"285", "time":1, "x":589.0000,"y":72.0574},{"pid":"286", "time":1, "x":589.0000,"y":72.0574},{"pid":"287", "time":1, "x":588.7572,"y":72.5473},{"pid":"288", "time":1, "x":588.2808,"y":73.1062},{"pid":"289", "time":1, "x":587.6109,"y":73.7171},{"pid":"290", "time":1, "x":586.7879,"y":74.3633},{"pid":"291", "time":1, "x":585.8521,"y":75.0278},{"pid":"292", "time":1, "x":584.8438,"y":75.6939},{"pid":"293", "time":1, "x":583.8032,"y":76.3447},{"pid":"294", "time":1, "x":582.7706,"y":76.9633},{"pid":"295", "time":1, "x":581.7863,"y":77.5330},{"pid":"296", "time":1, "x":580.8907,"y":78.0369},{"pid":"297", "time":1, "x":580.1239,"y":78.4581},{"pid":"298", "time":1, "x":579.5264,"y":78.7798},{"pid":"299", "time":1, "x":579.1383,"y":78.9852},{"pid":"300", "time":1, "x":579.0000,"y":79.0574},{"pid":"301", "time":1, "x":579.0000,"y":79.0574},{"pid":"302", "time":1, "x":579.0000,"y":79.0574},{"pid":"303", "time":1, "x":579.0000,"y":79.0574},{"pid":"304", "time":1, "x":579.0000,"y":79.0574},{"pid":"305", "time":1, "x":579.0000,"y":79.0574},{"pid":"306", "time":1, "x":579.0000,"y":79.0574},{"pid":"307", "time":1, "x":579.0000,"y":79.0574},{"pid":"308", "time":1, "x":579.0000,"y":79.0574},{"pid":"309", "time":1, "x":579.0000,"y":79.0574},{"pid":"310", "time":1, "x":579.0000,"y":79.0574},{"pid":"311", "time":1, "x":579.0000,"y":79.0574},{"pid":"312", "time":1, "x":579.0000,"y":79.0574},{"pid":"313", "time":1, "x":579.0000,"y":79.0574},{"pid":"314", "time":1, "x":579.0000,"y":79.0574},{"pid":"315", "time":1, "x":579.0000,"y":79.0574}]},{"id":"5", "points":[{"pid":"1", "time":1, "x":95.0000,"y":57.0574},{"pid":"2", "time":1, "x":95.0265,"y":57.0153},{"pid":"3", "time":1, "x":95.1026,"y":56.8972},{"pid":"4", "time":1, "x":95.2231,"y":56.7156},{"pid":"5", "time":1, "x":95.3829,"y":56.4828},{"pid":"6", "time":1, "x":95.5767,"y":56.2111},{"pid":"7", "time":1, "x":95.7994,"y":55.9129},{"pid":"8", "time":1, "x":96.0458,"y":55.6006},{"pid":"9", "time":1, "x":96.3108,"y":55.2865},{"pid":"10", "time":1, "x":96.5891,"y":54.9831},{"pid":"11", "time":1, "x":96.8756,"y":54.7025},{"pid":"12", "time":1, "x":97.1651,"y":54.4574},{"pid":"13", "time":1, "x":97.4525,"y":54.2599},{"pid":"14", "time":1, "x":97.7325,"y":54.1224},{"pid":"15", "time":1, "x":98.0000,"y":54.0574},{"pid":"16", "time":1, "x":98.0000,"y":54.0574},{"pid":"17", "time":1, "x":100.9542,"y":53.7892},{"pid":"18", "time":1, "x":103.6751,"y":53.5698},{"pid":"19", "time":1, "x":106.2146,"y":53.3946},{"pid":"20", "time":1, "x":108.6246,"y":53.2589},{"pid":"21", "time":1, "x":110.9568,"y":53.1581},{"pid":"22", "time":1, "x":113.2631,"y":53.0876},{"pid":"23", "time":1, "x":115.5953,"y":53.0427},{"pid":"24", "time":1, "x":118.0053,"y":53.0188},{"pid":"25", "time":1, "x":120.5448,"y":53.0113},{"pid":"26", "time":1, "x":123.2658,"y":53.0155},{"pid":"27", "time":1, "x":126.2199,"y":53.0269},{"pid":"28", "time":1, "x":129.4591,"y":53.0407},{"pid":"29", "time":1, "x":133.0352,"y":53.0524},{"pid":"30", "time":1, "x":137.0000,"y":53.0574},{"pid":"31", "time":1, "x":137.0000,"y":53.0574},{"pid":"32", "time":1, "x":152.4914,"y":53.0182},{"pid":"33", "time":1, "x":165.9877,"y":52.9144},{"pid":"34", "time":1, "x":177.8177,"y":52.7662},{"pid":"35", "time":1, "x":188.3100,"y":52.5943},{"pid":"36", "time":1, "x":197.7936,"y":52.4189},{"pid":"37", "time":1, "x":206.5972,"y":52.2605},{"pid":"38", "time":1, "x":215.0496,"y":52.1396},{"pid":"39", "time":1, "x":223.4795,"y":52.0765},{"pid":"40", "time":1, "x":232.2158,"y":52.0917},{"pid":"41", "time":1, "x":241.5872,"y":52.2057},{"pid":"42", "time":1, "x":251.9226,"y":52.4388},{"pid":"43", "time":1, "x":263.5506,"y":52.8115},{"pid":"44", "time":1, "x":276.8002,"y":53.3442},{"pid":"45", "time":1, "x":292.0000,"y":54.0574},{"pid":"46", "time":1, "x":292.0000,"y":54.0574},{"pid":"47", "time":1, "x":296.5636,"y":54.3182},{"pid":"48", "time":1, "x":300.5598,"y":54.6185},{"pid":"49", "time":1, "x":304.0811,"y":54.9631},{"pid":"50", "time":1, "x":307.2204,"y":55.3569},{"pid":"51", "time":1, "x":310.0703,"y":55.8046},{"pid":"52", "time":1, "x":312.7236,"y":56.3110},{"pid":"53", "time":1, "x":315.2731,"y":56.8811},{"pid":"54", "time":1, "x":317.8114,"y":57.5196},{"pid":"55", "time":1, "x":320.4313,"y":58.2313},{"pid":"56", "time":1, "x":323.2255,"y":59.0211},{"pid":"57", "time":1, "x":326.2868,"y":59.8938},{"pid":"58", "time":1, "x":329.7078,"y":60.8542},{"pid":"59", "time":1, "x":333.5813,"y":61.9071},{"pid":"60", "time":1, "x":338.0000,"y":63.0574},{"pid":"61", "time":1, "x":338.0000,"y":63.0574},{"pid":"62", "time":1, "x":339.3297,"y":63.4546},{"pid":"63", "time":1, "x":340.4948,"y":63.9142},{"pid":"64", "time":1, "x":341.5211,"y":64.4220},{"pid":"65", "time":1, "x":342.4343,"y":64.9634},{"pid":"66", "time":1, "x":343.2601,"y":65.5240},{"pid":"67", "time":1, "x":344.0242,"y":66.0895},{"pid":"68", "time":1, "x":344.7523,"y":66.6454},{"pid":"69", "time":1, "x":345.4701,"y":67.1773},{"pid":"70", "time":1, "x":346.2033,"y":67.6708},{"pid":"71", "time":1, "x":346.9777,"y":68.1114},{"pid":"72", "time":1, "x":347.8188,"y":68.4848},{"pid":"73", "time":1, "x":348.7524,"y":68.7765},{"pid":"74", "time":1, "x":349.8042,"y":68.9722},{"pid":"75", "time":1, "x":351.0000,"y":69.0574},{"pid":"76", "time":1, "x":351.0000,"y":69.0574},{"pid":"77", "time":1, "x":374.7289,"y":69.4407},{"pid":"78", "time":1, "x":398.8004,"y":69.6801},{"pid":"79", "time":1, "x":422.8783,"y":69.7941},{"pid":"80", "time":1, "x":446.6264,"y":69.8010},{"pid":"81", "time":1, "x":469.7084,"y":69.7195},{"pid":"82", "time":1, "x":491.7883,"y":69.5680},{"pid":"83", "time":1, "x":512.5296,"y":69.3650},{"pid":"84", "time":1, "x":531.5963,"y":69.1291},{"pid":"85", "time":1, "x":548.6521,"y":68.8787},{"pid":"86", "time":1, "x":563.3608,"y":68.6324},{"pid":"87", "time":1, "x":575.3861,"y":68.4086},{"pid":"88", "time":1, "x":584.3919,"y":68.2258},{"pid":"89", "time":1, "x":590.0419,"y":68.1026},{"pid":"90", "time":1, "x":592.0000,"y":68.0574},{"pid":"91", "time":1, "x":592.0000,"y":68.0574},{"pid":"92", "time":1, "x":592.0000,"y":68.0574},{"pid":"93", "time":1, "x":592.0000,"y":68.0574},{"pid":"94", "time":1, "x":592.0000,"y":68.0574},{"pid":"95", "time":1, "x":592.0000,"y":68.0574},{"pid":"96", "time":1, "x":592.0000,"y":68.0574},{"pid":"97", "time":1, "x":592.0000,"y":68.0574},{"pid":"98", "time":1, "x":592.0000,"y":68.0574},{"pid":"99", "time":1, "x":592.0000,"y":68.0574},{"pid":"100", "time":1, "x":592.0000,"y":68.0574},{"pid":"101", "time":1, "x":592.0000,"y":68.0574},{"pid":"102", "time":1, "x":592.0000,"y":68.0574},{"pid":"103", "time":1, "x":592.0000,"y":68.0574},{"pid":"104", "time":1, "x":592.0000,"y":68.0574},{"pid":"105", "time":1, "x":592.0000,"y":68.0574}]},{"id":"6", "points":[{"pid":"1", "time":1, "x":121.0000,"y":59.0574},{"pid":"2", "time":1, "x":121.0543,"y":59.1227},{"pid":"3", "time":1, "x":121.2130,"y":59.3097},{"pid":"4", "time":1, "x":121.4699,"y":59.6047},{"pid":"5", "time":1, "x":121.8188,"y":59.9938},{"pid":"6", "time":1, "x":122.2535,"y":60.4636},{"pid":"7", "time":1, "x":122.7677,"y":61.0001},{"pid":"8", "time":1, "x":123.3553,"y":61.5899},{"pid":"9", "time":1, "x":124.0100,"y":62.2192},{"pid":"10", "time":1, "x":124.7256,"y":62.8742},{"pid":"11", "time":1, "x":125.4960,"y":63.5414},{"pid":"12", "time":1, "x":126.3148,"y":64.2070},{"pid":"13", "time":1, "x":127.1759,"y":64.8573},{"pid":"14", "time":1, "x":128.0730,"y":65.4787},{"pid":"15", "time":1, "x":129.0000,"y":66.0574},{"pid":"16", "time":1, "x":129.0000,"y":66.0574},{"pid":"17", "time":1, "x":133.1015,"y":68.4867},{"pid":"18", "time":1, "x":136.6954,"y":70.6421},{"pid":"19", "time":1, "x":139.8691,"y":72.5619},{"pid":"20", "time":1, "x":142.7097,"y":74.2841},{"pid":"21", "time":1, "x":145.3046,"y":75.8472},{"pid":"22", "time":1, "x":147.7410,"y":77.2893},{"pid":"23", "time":1, "x":150.1062,"y":78.6485},{"pid":"24", "time":1, "x":152.4875,"y":79.9633},{"pid":"25", "time":1, "x":154.9721,"y":81.2717},{"pid":"26", "time":1, "x":157.6473,"y":82.6121},{"pid":"27", "time":1, "x":160.6005,"y":84.0226},{"pid":"28", "time":1, "x":163.9188,"y":85.5415},{"pid":"29", "time":1, "x":167.6895,"y":87.2070},{"pid":"30", "time":1, "x":172.0000,"y":89.0574},{"pid":"31", "time":1, "x":172.0000,"y":89.0574},{"pid":"32", "time":1, "x":174.1182,"y":89.8910},{"pid":"33", "time":1, "x":176.0948,"y":90.5470},{"pid":"34", "time":1, "x":177.9467,"y":91.0515},{"pid":"35", "time":1, "x":179.6913,"y":91.4305},{"pid":"36", "time":1, "x":181.3455,"y":91.7102},{"pid":"37", "time":1, "x":182.9266,"y":91.9165},{"pid":"38", "time":1, "x":184.4517,"y":92.0756},{"pid":"39", "time":1, "x":185.9380,"y":92.2136},{"pid":"40", "time":1, "x":187.4026,"y":92.3564},{"pid":"41", "time":1, "x":188.8626,"y":92.5303},{"pid":"42", "time":1, "x":190.3352,"y":92.7613},{"pid":"43", "time":1, "x":191.8375,"y":93.0754},{"pid":"44", "time":1, "x":193.3867,"y":93.4987},{"pid":"45", "time":1, "x":195.0000,"y":94.0574},{"pid":"46", "time":1, "x":195.0000,"y":94.0574},{"pid":"47", "time":1, "x":195.3026,"y":94.2305},{"pid":"48", "time":1, "x":195.5631,"y":94.4896},{"pid":"49", "time":1, "x":195.7885,"y":94.8201},{"pid":"50", "time":1, "x":195.9860,"y":95.2078},{"pid":"51", "time":1, "x":196.1627,"y":95.6381},{"pid":"52", "time":1, "x":196.3259,"y":96.0967},{"pid":"53", "time":1, "x":196.4826,"y":96.5693},{"pid":"54", "time":1, "x":196.6401,"y":97.0414},{"pid":"55", "time":1, "x":196.8054,"y":97.4985},{"pid":"56", "time":1, "x":196.9857,"y":97.9264},{"pid":"57", "time":1, "x":197.1881,"y":98.3107},{"pid":"58", "time":1, "x":197.4199,"y":98.6368},{"pid":"59", "time":1, "x":197.6881,"y":98.8905},{"pid":"60", "time":1, "x":198.0000,"y":99.0574},{"pid":"61", "time":1, "x":198.0000,"y":99.0574},{"pid":"62", "time":1, "x":201.8977,"y":100.3756},{"pid":"63", "time":1, "x":206.1088,"y":101.7010},{"pid":"64", "time":1, "x":210.5368,"y":103.0167},{"pid":"65", "time":1, "x":215.0853,"y":104.3061},{"pid":"66", "time":1, "x":219.6581,"y":105.5523},{"pid":"67", "time":1, "x":224.1586,"y":106.7386},{"pid":"68", "time":1, "x":228.4907,"y":107.8482},{"pid":"69", "time":1, "x":232.5577,"y":108.8642},{"pid":"70", "time":1, "x":236.2635,"y":109.7700},{"pid":"71", "time":1, "x":239.5117,"y":110.5487},{"pid":"72", "time":1, "x":242.2058,"y":111.1836},{"pid":"73", "time":1, "x":244.2494,"y":111.6578},{"pid":"74", "time":1, "x":245.5463,"y":111.9547},{"pid":"75", "time":1, "x":246.0000,"y":112.0574},{"pid":"76", "time":1, "x":246.0000,"y":112.0574},{"pid":"77", "time":1, "x":246.0000,"y":112.0574},{"pid":"78", "time":1, "x":246.0000,"y":112.0574},{"pid":"79", "time":1, "x":246.0000,"y":112.0574},{"pid":"80", "time":1, "x":246.0000,"y":112.0574},{"pid":"81", "time":1, "x":246.0000,"y":112.0574},{"pid":"82", "time":1, "x":246.0000,"y":112.0574},{"pid":"83", "time":1, "x":246.0000,"y":112.0574},{"pid":"84", "time":1, "x":246.0000,"y":112.0574},{"pid":"85", "time":1, "x":246.0000,"y":112.0574},{"pid":"86", "time":1, "x":246.0000,"y":112.0574},{"pid":"87", "time":1, "x":246.0000,"y":112.0574},{"pid":"88", "time":1, "x":246.0000,"y":112.0574},{"pid":"89", "time":1, "x":246.0000,"y":112.0574},{"pid":"90", "time":1, "x":246.0000,"y":112.0574}]},{"id":"7", "points":[{"pid":"1", "time":1, "x":181.0000,"y":55.0574},{"pid":"2", "time":1, "x":181.0745,"y":55.1545},{"pid":"3", "time":1, "x":181.2923,"y":55.4318},{"pid":"4", "time":1, "x":181.6449,"y":55.8680},{"pid":"5", "time":1, "x":182.1238,"y":56.4416},{"pid":"6", "time":1, "x":182.7207,"y":57.1315},{"pid":"7", "time":1, "x":183.4270,"y":57.9163},{"pid":"8", "time":1, "x":184.2342,"y":58.7748},{"pid":"9", "time":1, "x":185.1339,"y":59.6857},{"pid":"10", "time":1, "x":186.1177,"y":60.6276},{"pid":"11", "time":1, "x":187.1769,"y":61.5792},{"pid":"12", "time":1, "x":188.3033,"y":62.5193},{"pid":"13", "time":1, "x":189.4882,"y":63.4266},{"pid":"14", "time":1, "x":190.7233,"y":64.2797},{"pid":"15", "time":1, "x":192.0000,"y":65.0574},{"pid":"16", "time":1, "x":192.0000,"y":65.0574},{"pid":"17", "time":1, "x":195.8834,"y":67.2396},{"pid":"18", "time":1, "x":199.3010,"y":69.1252},{"pid":"19", "time":1, "x":202.3354,"y":70.7595},{"pid":"20", "time":1, "x":205.0689,"y":72.1874},{"pid":"21", "time":1, "x":207.5841,"y":73.4543},{"pid":"22", "time":1, "x":209.9633,"y":74.6053},{"pid":"23", "time":1, "x":212.2891,"y":75.6855},{"pid":"24", "time":1, "x":214.6439,"y":76.7400},{"pid":"25", "time":1, "x":217.1102,"y":77.8140},{"pid":"26", "time":1, "x":219.7704,"y":78.9527},{"pid":"27", "time":1, "x":222.7070,"y":80.2013},{"pid":"28", "time":1, "x":226.0025,"y":81.6048},{"pid":"29", "time":1, "x":229.7394,"y":83.2084},{"pid":"30", "time":1, "x":234.0000,"y":85.0574},{"pid":"31", "time":1, "x":234.0000,"y":85.0574},{"pid":"32", "time":1, "x":236.8305,"y":86.3013},{"pid":"33", "time":1, "x":239.2994,"y":87.3984},{"pid":"34", "time":1, "x":241.4679,"y":88.3678},{"pid":"35", "time":1, "x":243.3972,"y":89.2286},{"pid":"36", "time":1, "x":245.1485,"y":89.9998},{"pid":"37", "time":1, "x":246.7831,"y":90.7004},{"pid":"38", "time":1, "x":248.3621,"y":91.3497},{"pid":"39", "time":1, "x":249.9467,"y":91.9666},{"pid":"40", "time":1, "x":251.5982,"y":92.5703},{"pid":"41", "time":1, "x":253.3777,"y":93.1798},{"pid":"42", "time":1, "x":255.3464,"y":93.8142},{"pid":"43", "time":1, "x":257.5656,"y":94.4925},{"pid":"44", "time":1, "x":260.0964,"y":95.2339},{"pid":"45", "time":1, "x":263.0000,"y":96.0574},{"pid":"46", "time":1, "x":263.0000,"y":96.0574},{"pid":"47", "time":1, "x":264.9969,"y":96.5708},{"pid":"48", "time":1, "x":266.7760,"y":96.9413},{"pid":"49", "time":1, "x":268.3725,"y":97.1931},{"pid":"50", "time":1, "x":269.8220,"y":97.3505},{"pid":"51", "time":1, "x":271.1596,"y":97.4377},{"pid":"52", "time":1, "x":272.4209,"y":97.4788},{"pid":"53", "time":1, "x":273.6410,"y":97.4981},{"pid":"54", "time":1, "x":274.8553,"y":97.5199},{"pid":"55", "time":1, "x":276.0993,"y":97.5682},{"pid":"56", "time":1, "x":277.4082,"y":97.6675},{"pid":"57", "time":1, "x":278.8173,"y":97.8418},{"pid":"58", "time":1, "x":280.3621,"y":98.1154},{"pid":"59", "time":1, "x":282.0779,"y":98.5125},{"pid":"60", "time":1, "x":284.0000,"y":99.0574},{"pid":"61", "time":1, "x":284.0000,"y":99.0574},{"pid":"62", "time":1, "x":285.9264,"y":99.7006},{"pid":"63", "time":1, "x":287.8328,"y":100.4284},{"pid":"64", "time":1, "x":289.6995,"y":101.2198},{"pid":"65", "time":1, "x":291.5070,"y":102.0535},{"pid":"66", "time":1, "x":293.2355,"y":102.9083},{"pid":"67", "time":1, "x":294.8655,"y":103.7630},{"pid":"68", "time":1, "x":296.3772,"y":104.5965},{"pid":"69", "time":1, "x":297.7511,"y":105.3876},{"pid":"70", "time":1, "x":298.9676,"y":106.1151},{"pid":"71", "time":1, "x":300.0069,"y":106.7579},{"pid":"72", "time":1, "x":300.8494,"y":107.2946},{"pid":"73", "time":1, "x":301.4755,"y":107.7043},{"pid":"74", "time":1, "x":301.8656,"y":107.9656},{"pid":"75", "time":1, "x":302.0000,"y":108.0574},{"pid":"76", "time":1, "x":302.0000,"y":108.0574},{"pid":"77", "time":1, "x":302.0000,"y":108.0574},{"pid":"78", "time":1, "x":302.0000,"y":108.0574},{"pid":"79", "time":1, "x":302.0000,"y":108.0574},{"pid":"80", "time":1, "x":302.0000,"y":108.0574},{"pid":"81", "time":1, "x":302.0000,"y":108.0574},{"pid":"82", "time":1, "x":302.0000,"y":108.0574},{"pid":"83", "time":1, "x":302.0000,"y":108.0574},{"pid":"84", "time":1, "x":302.0000,"y":108.0574},{"pid":"85", "time":1, "x":302.0000,"y":108.0574},{"pid":"86", "time":1, "x":302.0000,"y":108.0574},{"pid":"87", "time":1, "x":302.0000,"y":108.0574},{"pid":"88", "time":1, "x":302.0000,"y":108.0574},{"pid":"89", "time":1, "x":302.0000,"y":108.0574},{"pid":"90", "time":1, "x":302.0000,"y":108.0574}]},{"id":"8", "points":[{"pid":"1", "time":1, "x":126.0000,"y":43.0574},{"pid":"2", "time":1, "x":126.0829,"y":42.9601},{"pid":"3", "time":1, "x":126.3249,"y":42.6811},{"pid":"4", "time":1, "x":126.7160,"y":42.2392},{"pid":"5", "time":1, "x":127.2461,"y":41.6534},{"pid":"6", "time":1, "x":127.9055,"y":40.9428},{"pid":"7", "time":1, "x":128.6839,"y":40.1262},{"pid":"8", "time":1, "x":129.5714,"y":39.2227},{"pid":"9", "time":1, "x":130.5581,"y":38.2512},{"pid":"10", "time":1, "x":131.6339,"y":37.2307},{"pid":"11", "time":1, "x":132.7888,"y":36.1802},{"pid":"12", "time":1, "x":134.0129,"y":35.1186},{"pid":"13", "time":1, "x":135.2961,"y":34.0650},{"pid":"14", "time":1, "x":136.6285,"y":33.0382},{"pid":"15", "time":1, "x":138.0000,"y":32.0574},{"pid":"16", "time":1, "x":138.0000,"y":32.0574},{"pid":"17", "time":1, "x":140.1429,"y":30.6325},{"pid":"18", "time":1, "x":142.0634,"y":29.4400},{"pid":"19", "time":1, "x":143.7978,"y":28.4408},{"pid":"20", "time":1, "x":145.3825,"y":27.5960},{"pid":"21", "time":1, "x":146.8539,"y":26.8665},{"pid":"22", "time":1, "x":148.2484,"y":26.2133},{"pid":"23", "time":1, "x":149.6024,"y":25.5975},{"pid":"24", "time":1, "x":150.9521,"y":24.9801},{"pid":"25", "time":1, "x":152.3341,"y":24.3220},{"pid":"26", "time":1, "x":153.7846,"y":23.5843},{"pid":"27", "time":1, "x":155.3401,"y":22.7280},{"pid":"28", "time":1, "x":157.0369,"y":21.7141},{"pid":"29", "time":1, "x":158.9114,"y":20.5035},{"pid":"30", "time":1, "x":161.0000,"y":19.0574},{"pid":"31", "time":1, "x":161.0000,"y":19.0574},{"pid":"32", "time":1, "x":162.2965,"y":18.0759},{"pid":"33", "time":1, "x":163.3946,"y":17.1371},{"pid":"34", "time":1, "x":164.3268,"y":16.2351},{"pid":"35", "time":1, "x":165.1261,"y":15.3640},{"pid":"36", "time":1, "x":165.8249,"y":14.5180},{"pid":"37", "time":1, "x":166.4562,"y":13.6911},{"pid":"38", "time":1, "x":167.0526,"y":12.8774},{"pid":"39", "time":1, "x":167.6469,"y":12.0710},{"pid":"40", "time":1, "x":168.2718,"y":11.2661},{"pid":"41", "time":1, "x":168.9599,"y":10.4568},{"pid":"42", "time":1, "x":169.7441,"y":9.6372},{"pid":"43", "time":1, "x":170.6570,"y":8.8013},{"pid":"44", "time":1, "x":171.7314,"y":7.9433},{"pid":"45", "time":1, "x":173.0000,"y":7.0574},{"pid":"46", "time":1, "x":173.0000,"y":7.0574},{"pid":"47", "time":1, "x":174.5378,"y":6.1102},{"pid":"48", "time":1, "x":176.1401,"y":5.2293},{"pid":"49", "time":1, "x":177.7782,"y":4.4155},{"pid":"50", "time":1, "x":179.4236,"y":3.6692},{"pid":"51", "time":1, "x":181.0477,"y":2.9911},{"pid":"52", "time":1, "x":182.6221,"y":2.3819},{"pid":"53", "time":1, "x":184.1182,"y":1.8420},{"pid":"54", "time":1, "x":185.5074,"y":1.3722},{"pid":"55", "time":1, "x":186.7612,"y":0.9729},{"pid":"56", "time":1, "x":187.8511,"y":0.6450},{"pid":"57", "time":1, "x":188.7484,"y":0.3888},{"pid":"58", "time":1, "x":189.4247,"y":0.2051},{"pid":"59", "time":1, "x":189.8514,"y":0.0944},{"pid":"60", "time":1, "x":190.0000,"y":0.0574},{"pid":"61", "time":1, "x":190.0000,"y":0.0574},{"pid":"62", "time":1, "x":190.0000,"y":0.0574},{"pid":"63", "time":1, "x":190.0000,"y":0.0574},{"pid":"64", "time":1, "x":190.0000,"y":0.0574},{"pid":"65", "time":1, "x":190.0000,"y":0.0574},{"pid":"66", "time":1, "x":190.0000,"y":0.0574},{"pid":"67", "time":1, "x":190.0000,"y":0.0574},{"pid":"68", "time":1, "x":190.0000,"y":0.0574},{"pid":"69", "time":1, "x":190.0000,"y":0.0574},{"pid":"70", "time":1, "x":190.0000,"y":0.0574},{"pid":"71", "time":1, "x":190.0000,"y":0.0574},{"pid":"72", "time":1, "x":190.0000,"y":0.0574},{"pid":"73", "time":1, "x":190.0000,"y":0.0574},{"pid":"74", "time":1, "x":190.0000,"y":0.0574},{"pid":"75", "time":1, "x":190.0000,"y":0.0574}]},{"id":"9", "points":[{"pid":"1", "time":1, "x":213.0000,"y":45.0574},{"pid":"2", "time":1, "x":213.0706,"y":44.9317},{"pid":"3", "time":1, "x":213.2765,"y":44.5731},{"pid":"4", "time":1, "x":213.6085,"y":44.0088},{"pid":"5", "time":1, "x":214.0576,"y":43.2663},{"pid":"6", "time":1, "x":214.6148,"y":42.3729},{"pid":"7", "time":1, "x":215.2710,"y":41.3559},{"pid":"8", "time":1, "x":216.0172,"y":40.2428},{"pid":"9", "time":1, "x":216.8443,"y":39.0609},{"pid":"10", "time":1, "x":217.7433,"y":37.8375},{"pid":"11", "time":1, "x":218.7052,"y":36.6001},{"pid":"12", "time":1, "x":219.7208,"y":35.3760},{"pid":"13", "time":1, "x":220.7812,"y":34.1926},{"pid":"14", "time":1, "x":221.8773,"y":33.0773},{"pid":"15", "time":1, "x":223.0000,"y":32.0574},{"pid":"16", "time":1, "x":223.0000,"y":32.0574},{"pid":"17", "time":1, "x":223.7098,"y":31.5110},{"pid":"18", "time":1, "x":224.3999,"y":31.0846},{"pid":"19", "time":1, "x":225.0755,"y":30.7584},{"pid":"20", "time":1, "x":225.7417,"y":30.5121},{"pid":"21", "time":1, "x":226.4035,"y":30.3260},{"pid":"22", "time":1, "x":227.0660,"y":30.1800},{"pid":"23", "time":1, "x":227.7342,"y":30.0541},{"pid":"24", "time":1, "x":228.4133,"y":29.9283},{"pid":"25", "time":1, "x":229.1083,"y":29.7827},{"pid":"26", "time":1, "x":229.8243,"y":29.5973},{"pid":"27", "time":1, "x":230.5664,"y":29.3520},{"pid":"28", "time":1, "x":231.3397,"y":29.0269},{"pid":"29", "time":1, "x":232.1492,"y":28.6020},{"pid":"30", "time":1, "x":233.0000,"y":28.0574},{"pid":"31", "time":1, "x":233.0000,"y":28.0574},{"pid":"32", "time":1, "x":235.0250,"y":26.5553},{"pid":"33", "time":1, "x":236.7778,"y":25.0957},{"pid":"34", "time":1, "x":238.3035,"y":23.6792},{"pid":"35", "time":1, "x":239.6473,"y":22.3061},{"pid":"36", "time":1, "x":240.8543,"y":20.9769},{"pid":"37", "time":1, "x":241.9695,"y":19.6920},{"pid":"38", "time":1, "x":243.0381,"y":18.4517},{"pid":"39", "time":1, "x":244.1051,"y":17.2566},{"pid":"40", "time":1, "x":245.2156,"y":16.1070},{"pid":"41", "time":1, "x":246.4148,"y":15.0035},{"pid":"42", "time":1, "x":247.7477,"y":13.9463},{"pid":"43", "time":1, "x":249.2595,"y":12.9359},{"pid":"44", "time":1, "x":250.9952,"y":11.9728},{"pid":"45", "time":1, "x":253.0000,"y":11.0574},{"pid":"46", "time":1, "x":253.0000,"y":11.0574},{"pid":"47", "time":1, "x":256.3640,"y":9.7926},{"pid":"48", "time":1, "x":259.8936,"y":8.6881},{"pid":"49", "time":1, "x":263.5226,"y":7.7333},{"pid":"50", "time":1, "x":267.1845,"y":6.9175},{"pid":"51", "time":1, "x":270.8128,"y":6.2300},{"pid":"52", "time":1, "x":274.3412,"y":5.6602},{"pid":"53", "time":1, "x":277.7032,"y":5.1974},{"pid":"54", "time":1, "x":280.8324,"y":4.8309},{"pid":"55", "time":1, "x":283.6624,"y":4.5501},{"pid":"56", "time":1, "x":286.1269,"y":4.3443},{"pid":"57", "time":1, "x":288.1592,"y":4.2028},{"pid":"58", "time":1, "x":289.6932,"y":4.1149},{"pid":"59", "time":1, "x":290.6622,"y":4.0700},{"pid":"60", "time":1, "x":291.0000,"y":4.0574},{"pid":"61", "time":1, "x":291.0000,"y":4.0574},{"pid":"62", "time":1, "x":291.0000,"y":4.0574},{"pid":"63", "time":1, "x":291.0000,"y":4.0574},{"pid":"64", "time":1, "x":291.0000,"y":4.0574},{"pid":"65", "time":1, "x":291.0000,"y":4.0574},{"pid":"66", "time":1, "x":291.0000,"y":4.0574},{"pid":"67", "time":1, "x":291.0000,"y":4.0574},{"pid":"68", "time":1, "x":291.0000,"y":4.0574},{"pid":"69", "time":1, "x":291.0000,"y":4.0574},{"pid":"70", "time":1, "x":291.0000,"y":4.0574},{"pid":"71", "time":1, "x":291.0000,"y":4.0574},{"pid":"72", "time":1, "x":291.0000,"y":4.0574},{"pid":"73", "time":1, "x":291.0000,"y":4.0574},{"pid":"74", "time":1, "x":291.0000,"y":4.0574},{"pid":"75", "time":1, "x":291.0000,"y":4.0574}]},{"id":"10", "points":[{"pid":"1", "time":1, "x":310.0000,"y":59.0574},{"pid":"2", "time":1, "x":310.0120,"y":58.9816},{"pid":"3", "time":1, "x":310.0489,"y":58.7650},{"pid":"4", "time":1, "x":310.1123,"y":58.4238},{"pid":"5", "time":1, "x":310.2038,"y":57.9741},{"pid":"6", "time":1, "x":310.3248,"y":57.4319},{"pid":"7", "time":1, "x":310.4770,"y":56.8136},{"pid":"8", "time":1, "x":310.6618,"y":56.1350},{"pid":"9", "time":1, "x":310.8808,"y":55.4126},{"pid":"10", "time":1, "x":311.1357,"y":54.6622},{"pid":"11", "time":1, "x":311.4278,"y":53.9001},{"pid":"12", "time":1, "x":311.7587,"y":53.1425},{"pid":"13", "time":1, "x":312.1300,"y":52.4054},{"pid":"14", "time":1, "x":312.5433,"y":51.7050},{"pid":"15", "time":1, "x":313.0000,"y":51.0574},{"pid":"16", "time":1, "x":313.0000,"y":51.0574},{"pid":"17", "time":1, "x":313.8400,"y":50.0296},{"pid":"18", "time":1, "x":314.6443,"y":49.1425},{"pid":"19", "time":1, "x":315.4199,"y":48.3730},{"pid":"20", "time":1, "x":316.1734,"y":47.6980},{"pid":"21", "time":1, "x":316.9118,"y":47.0943},{"pid":"22", "time":1, "x":317.6418,"y":46.5389},{"pid":"23", "time":1, "x":318.3703,"y":46.0085},{"pid":"24", "time":1, "x":319.1041,"y":45.4802},{"pid":"25", "time":1, "x":319.8500,"y":44.9307},{"pid":"26", "time":1, "x":320.6148,"y":44.3370},{"pid":"27", "time":1, "x":321.4054,"y":43.6759},{"pid":"28", "time":1, "x":322.2286,"y":42.9244},{"pid":"29", "time":1, "x":323.0912,"y":42.0592},{"pid":"30", "time":1, "x":324.0000,"y":41.0574},{"pid":"31", "time":1, "x":324.0000,"y":41.0574},{"pid":"32", "time":1, "x":324.2847,"y":40.6854},{"pid":"33", "time":1, "x":324.5021,"y":40.3130},{"pid":"34", "time":1, "x":324.6638,"y":39.9409},{"pid":"35", "time":1, "x":324.7809,"y":39.5697},{"pid":"36", "time":1, "x":324.8649,"y":39.2001},{"pid":"37", "time":1, "x":324.9270,"y":38.8329},{"pid":"38", "time":1, "x":324.9787,"y":38.4685},{"pid":"39", "time":1, "x":325.0313,"y":38.1078},{"pid":"40", "time":1, "x":325.0961,"y":37.7514},{"pid":"41", "time":1, "x":325.1844,"y":37.4000},{"pid":"42", "time":1, "x":325.3076,"y":37.0542},{"pid":"43", "time":1, "x":325.4770,"y":36.7147},{"pid":"44", "time":1, "x":325.7041,"y":36.3822},{"pid":"45", "time":1, "x":326.0000,"y":36.0574},{"pid":"46", "time":1, "x":326.0000,"y":36.0574},{"pid":"47", "time":1, "x":327.9124,"y":34.2112},{"pid":"48", "time":1, "x":329.6230,"y":32.5463},{"pid":"49", "time":1, "x":331.1718,"y":31.0362},{"pid":"50", "time":1, "x":332.5989,"y":29.6543},{"pid":"51", "time":1, "x":333.9445,"y":28.3742},{"pid":"52", "time":1, "x":335.2486,"y":27.1693},{"pid":"53", "time":1, "x":336.5514,"y":26.0132},{"pid":"54", "time":1, "x":337.8928,"y":24.8792},{"pid":"55", "time":1, "x":339.3131,"y":23.7410},{"pid":"56", "time":1, "x":340.8523,"y":22.5719},{"pid":"57", "time":1, "x":342.5504,"y":21.3456},{"pid":"58", "time":1, "x":344.4477,"y":20.0353},{"pid":"59", "time":1, "x":346.5842,"y":18.6148},{"pid":"60", "time":1, "x":349.0000,"y":17.0574},{"pid":"61", "time":1, "x":349.0000,"y":17.0574},{"pid":"62", "time":1, "x":350.8497,"y":15.8841},{"pid":"63", "time":1, "x":352.5086,"y":14.8456},{"pid":"64", "time":1, "x":354.0109,"y":13.9285},{"pid":"65", "time":1, "x":355.3909,"y":13.1197},{"pid":"66", "time":1, "x":356.6829,"y":12.4057},{"pid":"67", "time":1, "x":357.9210,"y":11.7733},{"pid":"68", "time":1, "x":359.1396,"y":11.2092},{"pid":"69", "time":1, "x":360.3729,"y":10.7002},{"pid":"70", "time":1, "x":361.6552,"y":10.2329},{"pid":"71", "time":1, "x":363.0207,"y":9.7940},{"pid":"72", "time":1, "x":364.5037,"y":9.3703},{"pid":"73", "time":1, "x":366.1384,"y":8.9485},{"pid":"74", "time":1, "x":367.9591,"y":8.5153},{"pid":"75", "time":1, "x":370.0000,"y":8.0574},{"pid":"76", "time":1, "x":370.0000,"y":8.0574},{"pid":"77", "time":1, "x":371.9146,"y":7.7011},{"pid":"78", "time":1, "x":373.8738,"y":7.4502},{"pid":"79", "time":1, "x":375.8478,"y":7.2921},{"pid":"80", "time":1, "x":377.8066,"y":7.2141},{"pid":"81", "time":1, "x":379.7205,"y":7.2036},{"pid":"82", "time":1, "x":381.5597,"y":7.2478},{"pid":"83", "time":1, "x":383.2942,"y":7.3343},{"pid":"84", "time":1, "x":384.8942,"y":7.4502},{"pid":"85", "time":1, "x":386.3300,"y":7.5830},{"pid":"86", "time":1, "x":387.5716,"y":7.7201},{"pid":"87", "time":1, "x":388.5893,"y":7.8487},{"pid":"88", "time":1, "x":389.3531,"y":7.9562},{"pid":"89", "time":1, "x":389.8333,"y":8.0300},{"pid":"90", "time":1, "x":390.0000,"y":8.0574},{"pid":"91", "time":1, "x":390.0000,"y":8.0574},{"pid":"92", "time":1, "x":390.0000,"y":8.0574},{"pid":"93", "time":1, "x":390.0000,"y":8.0574},{"pid":"94", "time":1, "x":390.0000,"y":8.0574},{"pid":"95", "time":1, "x":390.0000,"y":8.0574},{"pid":"96", "time":1, "x":390.0000,"y":8.0574},{"pid":"97", "time":1, "x":390.0000,"y":8.0574},{"pid":"98", "time":1, "x":390.0000,"y":8.0574},{"pid":"99", "time":1, "x":390.0000,"y":8.0574},{"pid":"100", "time":1, "x":390.0000,"y":8.0574},{"pid":"101", "time":1, "x":390.0000,"y":8.0574},{"pid":"102", "time":1, "x":390.0000,"y":8.0574},{"pid":"103", "time":1, "x":390.0000,"y":8.0574},{"pid":"104", "time":1, "x":390.0000,"y":8.0574},{"pid":"105", "time":1, "x":390.0000,"y":8.0574}]},{"id":"11", "points":[{"pid":"1", "time":1, "x":396.0000,"y":69.0574},{"pid":"2", "time":1, "x":396.1134,"y":68.9078},{"pid":"3", "time":1, "x":396.4375,"y":68.4768},{"pid":"4", "time":1, "x":396.9483,"y":67.7910},{"pid":"5", "time":1, "x":397.6217,"y":66.8772},{"pid":"6", "time":1, "x":398.4336,"y":65.7619},{"pid":"7", "time":1, "x":399.3599,"y":64.4718},{"pid":"8", "time":1, "x":400.3766,"y":63.0336},{"pid":"9", "time":1, "x":401.4595,"y":61.4739},{"pid":"10", "time":1, "x":402.5846,"y":59.8194},{"pid":"11", "time":1, "x":403.7278,"y":58.0967},{"pid":"12", "time":1, "x":404.8650,"y":56.3325},{"pid":"13", "time":1, "x":405.9722,"y":54.5535},{"pid":"14", "time":1, "x":407.0252,"y":52.7862},{"pid":"15", "time":1, "x":408.0000,"y":51.0574},{"pid":"16", "time":1, "x":408.0000,"y":51.0574},{"pid":"17", "time":1, "x":408.1205,"y":50.7720},{"pid":"18", "time":1, "x":408.1856,"y":50.4724},{"pid":"19", "time":1, "x":408.2047,"y":50.1621},{"pid":"20", "time":1, "x":408.1868,"y":49.8448},{"pid":"21", "time":1, "x":408.1412,"y":49.5239},{"pid":"22", "time":1, "x":408.0771,"y":49.2030},{"pid":"23", "time":1, "x":408.0036,"y":48.8855},{"pid":"24", "time":1, "x":407.9300,"y":48.5751},{"pid":"25", "time":1, "x":407.8654,"y":48.2752},{"pid":"26", "time":1, "x":407.8191,"y":47.9893},{"pid":"27", "time":1, "x":407.8002,"y":47.7211},{"pid":"28", "time":1, "x":407.8179,"y":47.4740},{"pid":"29", "time":1, "x":407.8814,"y":47.2516},{"pid":"30", "time":1, "x":408.0000,"y":47.0574},{"pid":"31", "time":1, "x":408.0000,"y":47.0574},{"pid":"32", "time":1, "x":408.9542,"y":45.9079},{"pid":"33", "time":1, "x":409.8529,"y":44.8235},{"pid":"34", "time":1, "x":410.7146,"y":43.7939},{"pid":"35", "time":1, "x":411.5576,"y":42.8082},{"pid":"36", "time":1, "x":412.4003,"y":41.8562},{"pid":"37", "time":1, "x":413.2610,"y":40.9271},{"pid":"38", "time":1, "x":414.1581,"y":40.0105},{"pid":"39", "time":1, "x":415.1100,"y":39.0958},{"pid":"40", "time":1, "x":416.1351,"y":38.1725},{"pid":"41", "time":1, "x":417.2516,"y":37.2300},{"pid":"42", "time":1, "x":418.4780,"y":36.2578},{"pid":"43", "time":1, "x":419.8326,"y":35.2453},{"pid":"44", "time":1, "x":421.3338,"y":34.1820},{"pid":"45", "time":1, "x":423.0000,"y":33.0574},{"pid":"46", "time":1, "x":423.0000,"y":33.0574},{"pid":"47", "time":1, "x":426.5378,"y":30.6980},{"pid":"48", "time":1, "x":429.6868,"y":28.5628},{"pid":"49", "time":1, "x":432.5126,"y":26.6287},{"pid":"50", "time":1, "x":435.0807,"y":24.8728},{"pid":"51", "time":1, "x":437.4565,"y":23.2721},{"pid":"52", "time":1, "x":439.7057,"y":21.8036},{"pid":"53", "time":1, "x":441.8936,"y":20.4443},{"pid":"54", "time":1, "x":444.0860,"y":19.1712},{"pid":"55", "time":1, "x":446.3481,"y":17.9615},{"pid":"56", "time":1, "x":448.7457,"y":16.7920},{"pid":"57", "time":1, "x":451.3441,"y":15.6398},{"pid":"58", "time":1, "x":454.2090,"y":14.4820},{"pid":"59", "time":1, "x":457.4058,"y":13.2955},{"pid":"60", "time":1, "x":461.0000,"y":12.0574},{"pid":"61", "time":1, "x":461.0000,"y":12.0574},{"pid":"62", "time":1, "x":463.1918,"y":11.4483},{"pid":"63", "time":1, "x":465.4990,"y":11.0193},{"pid":"64", "time":1, "x":467.8770,"y":10.7490},{"pid":"65", "time":1, "x":470.2814,"y":10.6157},{"pid":"66", "time":1, "x":472.6679,"y":10.5976},{"pid":"67", "time":1, "x":474.9918,"y":10.6733},{"pid":"68", "time":1, "x":477.2088,"y":10.8211},{"pid":"69", "time":1, "x":479.2745,"y":11.0193},{"pid":"70", "time":1, "x":481.1443,"y":11.2464},{"pid":"71", "time":1, "x":482.7738,"y":11.4807},{"pid":"72", "time":1, "x":484.1186,"y":11.7005},{"pid":"73", "time":1, "x":485.1342,"y":11.8844},{"pid":"74", "time":1, "x":485.7761,"y":12.0105},{"pid":"75", "time":1, "x":486.0000,"y":12.0574},{"pid":"76", "time":1, "x":486.0000,"y":12.0574},{"pid":"77", "time":1, "x":486.0000,"y":12.0574},{"pid":"78", "time":1, "x":486.0000,"y":12.0574},{"pid":"79", "time":1, "x":486.0000,"y":12.0574},{"pid":"80", "time":1, "x":486.0000,"y":12.0574},{"pid":"81", "time":1, "x":486.0000,"y":12.0574},{"pid":"82", "time":1, "x":486.0000,"y":12.0574},{"pid":"83", "time":1, "x":486.0000,"y":12.0574},{"pid":"84", "time":1, "x":486.0000,"y":12.0574},{"pid":"85", "time":1, "x":486.0000,"y":12.0574},{"pid":"86", "time":1, "x":486.0000,"y":12.0574},{"pid":"87", "time":1, "x":486.0000,"y":12.0574},{"pid":"88", "time":1, "x":486.0000,"y":12.0574},{"pid":"89", "time":1, "x":486.0000,"y":12.0574},{"pid":"90", "time":1, "x":486.0000,"y":12.0574}]},{"id":"12", "points":[{"pid":"1", "time":1, "x":477.0000,"y":66.0574},{"pid":"2", "time":1, "x":477.0663,"y":65.9301},{"pid":"3", "time":1, "x":477.2604,"y":65.5640},{"pid":"4", "time":1, "x":477.5753,"y":64.9825},{"pid":"5", "time":1, "x":478.0040,"y":64.2089},{"pid":"6", "time":1, "x":478.5395,"y":63.2666},{"pid":"7", "time":1, "x":479.1746,"y":62.1790},{"pid":"8", "time":1, "x":479.9024,"y":60.9696},{"pid":"9", "time":1, "x":480.7158,"y":59.6618},{"pid":"10", "time":1, "x":481.6078,"y":58.2788},{"pid":"11", "time":1, "x":482.5713,"y":56.8443},{"pid":"12", "time":1, "x":483.5993,"y":55.3814},{"pid":"13", "time":1, "x":484.6848,"y":53.9137},{"pid":"14", "time":1, "x":485.8207,"y":52.4646},{"pid":"15", "time":1, "x":487.0000,"y":51.0574},{"pid":"16", "time":1, "x":487.0000,"y":51.0574},{"pid":"17", "time":1, "x":487.8001,"y":50.1376},{"pid":"18", "time":1, "x":488.5222,"y":49.3137},{"pid":"19", "time":1, "x":489.1824,"y":48.5752},{"pid":"20", "time":1, "x":489.7970,"y":47.9113},{"pid":"21", "time":1, "x":490.3822,"y":47.3116},{"pid":"22", "time":1, "x":490.9542,"y":46.7656},{"pid":"23", "time":1, "x":491.5292,"y":46.2625},{"pid":"24", "time":1, "x":492.1234,"y":45.7919},{"pid":"25", "time":1, "x":492.7531,"y":45.3431},{"pid":"26", "time":1, "x":493.4343,"y":44.9057},{"pid":"27", "time":1, "x":494.1835,"y":44.4689},{"pid":"28", "time":1, "x":495.0166,"y":44.0224},{"pid":"29", "time":1, "x":495.9501,"y":43.5554},{"pid":"30", "time":1, "x":497.0000,"y":43.0574},{"pid":"31", "time":1, "x":497.0000,"y":43.0574},{"pid":"32", "time":1, "x":498.5639,"y":42.3703},{"pid":"33", "time":1, "x":499.9742,"y":41.8258},{"pid":"34", "time":1, "x":501.2585,"y":41.4010},{"pid":"35", "time":1, "x":502.4445,"y":41.0729},{"pid":"36", "time":1, "x":503.5600,"y":40.8186},{"pid":"37", "time":1, "x":504.6327,"y":40.6150},{"pid":"38", "time":1, "x":505.6903,"y":40.4392},{"pid":"39", "time":1, "x":506.7605,"y":40.2682},{"pid":"40", "time":1, "x":507.8712,"y":40.0791},{"pid":"41", "time":1, "x":509.0499,"y":39.8489},{"pid":"42", "time":1, "x":510.3244,"y":39.5545},{"pid":"43", "time":1, "x":511.7224,"y":39.1732},{"pid":"44", "time":1, "x":513.2717,"y":38.6818},{"pid":"45", "time":1, "x":515.0000,"y":38.0574},{"pid":"46", "time":1, "x":515.0000,"y":38.0574},{"pid":"47", "time":1, "x":516.6331,"y":37.3882},{"pid":"48", "time":1, "x":518.0571,"y":36.7204},{"pid":"49", "time":1, "x":519.3054,"y":36.0572},{"pid":"50", "time":1, "x":520.4114,"y":35.4022},{"pid":"51", "time":1, "x":521.4087,"y":34.7588},{"pid":"52", "time":1, "x":522.3305,"y":34.1305},{"pid":"53", "time":1, "x":523.2103,"y":33.5206},{"pid":"54", "time":1, "x":524.0816,"y":32.9326},{"pid":"55", "time":1, "x":524.9776,"y":32.3700},{"pid":"56", "time":1, "x":525.9320,"y":31.8361},{"pid":"57", "time":1, "x":526.9779,"y":31.3345},{"pid":"58", "time":1, "x":528.1490,"y":30.8686},{"pid":"59", "time":1, "x":529.4785,"y":30.4417},{"pid":"60", "time":1, "x":531.0000,"y":30.0574},{"pid":"61", "time":1, "x":531.0000,"y":30.0574},{"pid":"62", "time":1, "x":532.8713,"y":29.7063},{"pid":"63", "time":1, "x":534.8000,"y":29.4591},{"pid":"64", "time":1, "x":536.7547,"y":29.3033},{"pid":"65", "time":1, "x":538.7040,"y":29.2265},{"pid":"66", "time":1, "x":540.6167,"y":29.2161},{"pid":"67", "time":1, "x":542.4612,"y":29.2597},{"pid":"68", "time":1, "x":544.2062,"y":29.3449},{"pid":"69", "time":1, "x":545.8204,"y":29.4591},{"pid":"70", "time":1, "x":547.2723,"y":29.5900},{"pid":"71", "time":1, "x":548.5306,"y":29.7250},{"pid":"72", "time":1, "x":549.5639,"y":29.8517},{"pid":"73", "time":1, "x":550.3408,"y":29.9577},{"pid":"74", "time":1, "x":550.8300,"y":30.0304},{"pid":"75", "time":1, "x":551.0000,"y":30.0574},{"pid":"76", "time":1, "x":551.0000,"y":30.0574},{"pid":"77", "time":1, "x":551.0000,"y":30.0574},{"pid":"78", "time":1, "x":551.0000,"y":30.0574},{"pid":"79", "time":1, "x":551.0000,"y":30.0574},{"pid":"80", "time":1, "x":551.0000,"y":30.0574},{"pid":"81", "time":1, "x":551.0000,"y":30.0574},{"pid":"82", "time":1, "x":551.0000,"y":30.0574},{"pid":"83", "time":1, "x":551.0000,"y":30.0574},{"pid":"84", "time":1, "x":551.0000,"y":30.0574},{"pid":"85", "time":1, "x":551.0000,"y":30.0574},{"pid":"86", "time":1, "x":551.0000,"y":30.0574},{"pid":"87", "time":1, "x":551.0000,"y":30.0574},{"pid":"88", "time":1, "x":551.0000,"y":30.0574},{"pid":"89", "time":1, "x":551.0000,"y":30.0574},{"pid":"90", "time":1, "x":551.0000,"y":30.0574}]},{"id":"13", "points":[{"pid":"1", "time":1, "x":309.0000,"y":56.0574},{"pid":"2", "time":1, "x":309.1150,"y":56.3677},{"pid":"3", "time":1, "x":309.4546,"y":57.2534},{"pid":"4", "time":1, "x":310.0103,"y":58.6467},{"pid":"5", "time":1, "x":310.7738,"y":60.4796},{"pid":"6", "time":1, "x":311.7368,"y":62.6844},{"pid":"7", "time":1, "x":312.8909,"y":65.1930},{"pid":"8", "time":1, "x":314.2277,"y":67.9376},{"pid":"9", "time":1, "x":315.7388,"y":70.8504},{"pid":"10", "time":1, "x":317.4160,"y":73.8635},{"pid":"11", "time":1, "x":319.2509,"y":76.9090},{"pid":"12", "time":1, "x":321.2351,"y":79.9190},{"pid":"13", "time":1, "x":323.3603,"y":82.8256},{"pid":"14", "time":1, "x":325.6180,"y":85.5611},{"pid":"15", "time":1, "x":328.0000,"y":88.0574},{"pid":"16", "time":1, "x":328.0000,"y":88.0574},{"pid":"17", "time":1, "x":330.9972,"y":90.7482},{"pid":"18", "time":1, "x":334.2381,"y":93.3150},{"pid":"19", "time":1, "x":337.6482,"y":95.7458},{"pid":"20", "time":1, "x":341.1527,"y":98.0286},{"pid":"21", "time":1, "x":344.6774,"y":100.1512},{"pid":"22", "time":1, "x":348.1474,"y":102.1016},{"pid":"23", "time":1, "x":351.4885,"y":103.8677},{"pid":"24", "time":1, "x":354.6259,"y":105.4375},{"pid":"25", "time":1, "x":357.4852,"y":106.7988},{"pid":"26", "time":1, "x":359.9917,"y":107.9397},{"pid":"27", "time":1, "x":362.0710,"y":108.8481},{"pid":"28", "time":1, "x":363.6485,"y":109.5119},{"pid":"29", "time":1, "x":364.6497,"y":109.9190},{"pid":"30", "time":1, "x":365.0000,"y":110.0574},{"pid":"31", "time":1, "x":365.0000,"y":110.0574},{"pid":"32", "time":1, "x":365.0000,"y":110.0574},{"pid":"33", "time":1, "x":365.0000,"y":110.0574},{"pid":"34", "time":1, "x":365.0000,"y":110.0574},{"pid":"35", "time":1, "x":365.0000,"y":110.0574},{"pid":"36", "time":1, "x":365.0000,"y":110.0574},{"pid":"37", "time":1, "x":365.0000,"y":110.0574},{"pid":"38", "time":1, "x":365.0000,"y":110.0574},{"pid":"39", "time":1, "x":365.0000,"y":110.0574},{"pid":"40", "time":1, "x":365.0000,"y":110.0574},{"pid":"41", "time":1, "x":365.0000,"y":110.0574},{"pid":"42", "time":1, "x":365.0000,"y":110.0574},{"pid":"43", "time":1, "x":365.0000,"y":110.0574},{"pid":"44", "time":1, "x":365.0000,"y":110.0574},{"pid":"45", "time":1, "x":365.0000,"y":110.0574}]},{"id":"14", "points":[{"pid":"1", "time":1, "x":398.0000,"y":75.0574},{"pid":"2", "time":1, "x":398.3755,"y":75.2698},{"pid":"3", "time":1, "x":399.4651,"y":75.8795},{"pid":"4", "time":1, "x":401.2130,"y":76.8448},{"pid":"5", "time":1, "x":403.5638,"y":78.1242},{"pid":"6", "time":1, "x":406.4619,"y":79.6763},{"pid":"7", "time":1, "x":409.8517,"y":81.4593},{"pid":"8", "time":1, "x":413.6775,"y":83.4319},{"pid":"9", "time":1, "x":417.8838,"y":85.5525},{"pid":"10", "time":1, "x":422.4151,"y":87.7795},{"pid":"11", "time":1, "x":427.2157,"y":90.0715},{"pid":"12", "time":1, "x":432.2301,"y":92.3867},{"pid":"13", "time":1, "x":437.4027,"y":94.6838},{"pid":"14", "time":1, "x":442.6778,"y":96.9212},{"pid":"15", "time":1, "x":448.0000,"y":99.0574},{"pid":"16", "time":1, "x":448.0000,"y":99.0574},{"pid":"17", "time":1, "x":450.1443,"y":99.8248},{"pid":"18", "time":1, "x":452.3263,"y":100.4874},{"pid":"19", "time":1, "x":454.5145,"y":101.0529},{"pid":"20", "time":1, "x":456.6776,"y":101.5288},{"pid":"21", "time":1, "x":458.7841,"y":101.9230},{"pid":"22", "time":1, "x":460.8024,"y":102.2430},{"pid":"23", "time":1, "x":462.7011,"y":102.4967},{"pid":"24", "time":1, "x":464.4487,"y":102.6915},{"pid":"25", "time":1, "x":466.0138,"y":102.8353},{"pid":"26", "time":1, "x":467.3649,"y":102.9358},{"pid":"27", "time":1, "x":468.4706,"y":103.0005},{"pid":"28", "time":1, "x":469.2993,"y":103.0372},{"pid":"29", "time":1, "x":469.8196,"y":103.0536},{"pid":"30", "time":1, "x":470.0000,"y":103.0574},{"pid":"31", "time":1, "x":470.0000,"y":103.0574},{"pid":"32", "time":1, "x":470.0000,"y":103.0574},{"pid":"33", "time":1, "x":470.0000,"y":103.0574},{"pid":"34", "time":1, "x":470.0000,"y":103.0574},{"pid":"35", "time":1, "x":470.0000,"y":103.0574},{"pid":"36", "time":1, "x":470.0000,"y":103.0574},{"pid":"37", "time":1, "x":470.0000,"y":103.0574},{"pid":"38", "time":1, "x":470.0000,"y":103.0574},{"pid":"39", "time":1, "x":470.0000,"y":103.0574},{"pid":"40", "time":1, "x":470.0000,"y":103.0574},{"pid":"41", "time":1, "x":470.0000,"y":103.0574},{"pid":"42", "time":1, "x":470.0000,"y":103.0574},{"pid":"43", "time":1, "x":470.0000,"y":103.0574},{"pid":"44", "time":1, "x":470.0000,"y":103.0574},{"pid":"45", "time":1, "x":470.0000,"y":103.0574}]},{"id":"15", "points":[{"pid":"1", "time":1, "x":492.0000,"y":74.0574},{"pid":"2", "time":1, "x":491.9844,"y":74.0855},{"pid":"3", "time":1, "x":491.9410,"y":74.1645},{"pid":"4", "time":1, "x":491.8744,"y":74.2860},{"pid":"5", "time":1, "x":491.7896,"y":74.4417},{"pid":"6", "time":1, "x":491.6913,"y":74.6233},{"pid":"7", "time":1, "x":491.5845,"y":74.8226},{"pid":"8", "time":1, "x":491.4739,"y":75.0313},{"pid":"9", "time":1, "x":491.3644,"y":75.2410},{"pid":"10", "time":1, "x":491.2607,"y":75.4435},{"pid":"11", "time":1, "x":491.1678,"y":75.6304},{"pid":"12", "time":1, "x":491.0905,"y":75.7936},{"pid":"13", "time":1, "x":491.0335,"y":75.9247},{"pid":"14", "time":1, "x":491.0017,"y":76.0154},{"pid":"15", "time":1, "x":491.0000,"y":76.0574},{"pid":"16", "time":1, "x":491.0000,"y":76.0574},{"pid":"17", "time":1, "x":491.1920,"y":76.2379},{"pid":"18", "time":1, "x":491.4386,"y":76.4487},{"pid":"19", "time":1, "x":491.7380,"y":76.6865},{"pid":"20", "time":1, "x":492.0884,"y":76.9475},{"pid":"21", "time":1, "x":492.4880,"y":77.2282},{"pid":"22", "time":1, "x":492.9350,"y":77.5251},{"pid":"23", "time":1, "x":493.4275,"y":77.8347},{"pid":"24", "time":1, "x":493.9638,"y":78.1533},{"pid":"25", "time":1, "x":494.5421,"y":78.4775},{"pid":"26", "time":1, "x":495.1606,"y":78.8037},{"pid":"27", "time":1, "x":495.8174,"y":79.1283},{"pid":"28", "time":1, "x":496.5108,"y":79.4479},{"pid":"29", "time":1, "x":497.2389,"y":79.7587},{"pid":"30", "time":1, "x":498.0000,"y":80.0574},{"pid":"31", "time":1, "x":498.0000,"y":80.0574},{"pid":"32", "time":1, "x":499.6172,"y":80.6744},{"pid":"33", "time":1, "x":501.0401,"y":81.2343},{"pid":"34", "time":1, "x":502.3017,"y":81.7413},{"pid":"35", "time":1, "x":503.4352,"y":82.1997},{"pid":"36", "time":1, "x":504.4737,"y":82.6139},{"pid":"37", "time":1, "x":505.4501,"y":82.9881},{"pid":"38", "time":1, "x":506.3977,"y":83.3266},{"pid":"39", "time":1, "x":507.3494,"y":83.6338},{"pid":"40", "time":1, "x":508.3384,"y":83.9138},{"pid":"41", "time":1, "x":509.3977,"y":84.1710},{"pid":"42", "time":1, "x":510.5604,"y":84.4096},{"pid":"43", "time":1, "x":511.8597,"y":84.6341},{"pid":"44", "time":1, "x":513.3285,"y":84.8485},{"pid":"45", "time":1, "x":515.0000,"y":85.0574},{"pid":"46", "time":1, "x":515.0000,"y":85.0574},{"pid":"47", "time":1, "x":517.4818,"y":85.3033},{"pid":"48", "time":1, "x":519.6821,"y":85.4395},{"pid":"49", "time":1, "x":521.6473,"y":85.4840},{"pid":"50", "time":1, "x":523.4237,"y":85.4548},{"pid":"51", "time":1, "x":525.0577,"y":85.3698},{"pid":"52", "time":1, "x":526.5955,"y":85.2469},{"pid":"53", "time":1, "x":528.0836,"y":85.1041},{"pid":"54", "time":1, "x":529.5683,"y":84.9595},{"pid":"55", "time":1, "x":531.0959,"y":84.8309},{"pid":"56", "time":1, "x":532.7127,"y":84.7363},{"pid":"57", "time":1, "x":534.4653,"y":84.6937},{"pid":"58", "time":1, "x":536.3997,"y":84.7210},{"pid":"59", "time":1, "x":538.5625,"y":84.8363},{"pid":"60", "time":1, "x":541.0000,"y":85.0574},{"pid":"61", "time":1, "x":541.0000,"y":85.0574},{"pid":"62", "time":1, "x":542.0665,"y":85.2092},{"pid":"63", "time":1, "x":543.0027,"y":85.4132},{"pid":"64", "time":1, "x":543.8303,"y":85.6614},{"pid":"65", "time":1, "x":544.5712,"y":85.9460},{"pid":"66", "time":1, "x":545.2471,"y":86.2591},{"pid":"67", "time":1, "x":545.8797,"y":86.5927},{"pid":"68", "time":1, "x":546.4910,"y":86.9391},{"pid":"69", "time":1, "x":547.1026,"y":87.2903},{"pid":"70", "time":1, "x":547.7364,"y":87.6385},{"pid":"71", "time":1, "x":548.4141,"y":87.9757},{"pid":"72", "time":1, "x":549.1575,"y":88.2941},{"pid":"73", "time":1, "x":549.9885,"y":88.5857},{"pid":"74", "time":1, "x":550.9287,"y":88.8428},{"pid":"75", "time":1, "x":552.0000,"y":89.0574},{"pid":"76", "time":1, "x":552.0000,"y":89.0574},{"pid":"77", "time":1, "x":553.2887,"y":89.2406},{"pid":"78", "time":1, "x":554.5934,"y":89.3696},{"pid":"79", "time":1, "x":555.8961,"y":89.4509},{"pid":"80", "time":1, "x":557.1790,"y":89.4910},{"pid":"81", "time":1, "x":558.4243,"y":89.4964},{"pid":"82", "time":1, "x":559.6143,"y":89.4736},{"pid":"83", "time":1, "x":560.7310,"y":89.4292},{"pid":"84", "time":1, "x":561.7566,"y":89.3696},{"pid":"85", "time":1, "x":562.6734,"y":89.3013},{"pid":"86", "time":1, "x":563.4634,"y":89.2308},{"pid":"87", "time":1, "x":564.1089,"y":89.1647},{"pid":"88", "time":1, "x":564.5921,"y":89.1094},{"pid":"89", "time":1, "x":564.8951,"y":89.0715},{"pid":"90", "time":1, "x":565.0000,"y":89.0574},{"pid":"91", "time":1, "x":565.0000,"y":89.0574},{"pid":"92", "time":1, "x":565.0000,"y":89.0574},{"pid":"93", "time":1, "x":565.0000,"y":89.0574},{"pid":"94", "time":1, "x":565.0000,"y":89.0574},{"pid":"95", "time":1, "x":565.0000,"y":89.0574},{"pid":"96", "time":1, "x":565.0000,"y":89.0574},{"pid":"97", "time":1, "x":565.0000,"y":89.0574},{"pid":"98", "time":1, "x":565.0000,"y":89.0574},{"pid":"99", "time":1, "x":565.0000,"y":89.0574},{"pid":"100", "time":1, "x":565.0000,"y":89.0574},{"pid":"101", "time":1, "x":565.0000,"y":89.0574},{"pid":"102", "time":1, "x":565.0000,"y":89.0574},{"pid":"103", "time":1, "x":565.0000,"y":89.0574},{"pid":"104", "time":1, "x":565.0000,"y":89.0574},{"pid":"105", "time":1, "x":565.0000,"y":89.0574}]},{"id":"16", "points":[{"pid":"1", "time":1, "x":547.0000,"y":65.0574},{"pid":"2", "time":1, "x":547.1576,"y":65.0550},{"pid":"3", "time":1, "x":547.6131,"y":65.0455},{"pid":"4", "time":1, "x":548.3412,"y":65.0253},{"pid":"5", "time":1, "x":549.3159,"y":64.9907},{"pid":"6", "time":1, "x":550.5119,"y":64.9381},{"pid":"7", "time":1, "x":551.9034,"y":64.8639},{"pid":"8", "time":1, "x":553.4648,"y":64.7644},{"pid":"9", "time":1, "x":555.1705,"y":64.6361},{"pid":"10", "time":1, "x":556.9949,"y":64.4753},{"pid":"11", "time":1, "x":558.9123,"y":64.2784},{"pid":"12", "time":1, "x":560.8971,"y":64.0418},{"pid":"13", "time":1, "x":562.9238,"y":63.7618},{"pid":"14", "time":1, "x":564.9666,"y":63.4349},{"pid":"15", "time":1, "x":567.0000,"y":63.0574},{"pid":"16", "time":1, "x":567.0000,"y":63.0574},{"pid":"17", "time":1, "x":568.0091,"y":62.8514},{"pid":"18", "time":1, "x":568.9082,"y":62.6572},{"pid":"19", "time":1, "x":569.7136,"y":62.4689},{"pid":"20", "time":1, "x":570.4412,"y":62.2803},{"pid":"21", "time":1, "x":571.1074,"y":62.0855},{"pid":"22", "time":1, "x":571.7281,"y":61.8784},{"pid":"23", "time":1, "x":572.3197,"y":61.6530},{"pid":"24", "time":1, "x":572.8983,"y":61.4033},{"pid":"25", "time":1, "x":573.4799,"y":61.1233},{"pid":"26", "time":1, "x":574.0808,"y":60.8069},{"pid":"27", "time":1, "x":574.7171,"y":60.4481},{"pid":"28", "time":1, "x":575.4050,"y":60.0410},{"pid":"29", "time":1, "x":576.1605,"y":59.5794},{"pid":"30", "time":1, "x":577.0000,"y":59.0574},{"pid":"31", "time":1, "x":577.0000,"y":59.0574},{"pid":"32", "time":1, "x":577.6839,"y":58.5972},{"pid":"33", "time":1, "x":578.3487,"y":58.0898},{"pid":"34", "time":1, "x":578.9895,"y":57.5483},{"pid":"35", "time":1, "x":579.6011,"y":56.9856},{"pid":"36", "time":1, "x":580.1785,"y":56.4148},{"pid":"37", "time":1, "x":580.7167,"y":55.8489},{"pid":"38", "time":1, "x":581.2105,"y":55.3008},{"pid":"39", "time":1, "x":581.6548,"y":54.7837},{"pid":"40", "time":1, "x":582.0448,"y":54.3104},{"pid":"41", "time":1, "x":582.3751,"y":53.8940},{"pid":"42", "time":1, "x":582.6409,"y":53.5475},{"pid":"43", "time":1, "x":582.8370,"y":53.2839},{"pid":"44", "time":1, "x":582.9584,"y":53.1162},{"pid":"45", "time":1, "x":583.0000,"y":53.0574},{"pid":"46", "time":1, "x":583.0000,"y":53.0574},{"pid":"47", "time":1, "x":583.0000,"y":53.0574},{"pid":"48", "time":1, "x":583.0000,"y":53.0574},{"pid":"49", "time":1, "x":583.0000,"y":53.0574},{"pid":"50", "time":1, "x":583.0000,"y":53.0574},{"pid":"51", "time":1, "x":583.0000,"y":53.0574},{"pid":"52", "time":1, "x":583.0000,"y":53.0574},{"pid":"53", "time":1, "x":583.0000,"y":53.0574},{"pid":"54", "time":1, "x":583.0000,"y":53.0574},{"pid":"55", "time":1, "x":583.0000,"y":53.0574},{"pid":"56", "time":1, "x":583.0000,"y":53.0574},{"pid":"57", "time":1, "x":583.0000,"y":53.0574},{"pid":"58", "time":1, "x":583.0000,"y":53.0574},{"pid":"59", "time":1, "x":583.0000,"y":53.0574},{"pid":"60", "time":1, "x":583.0000,"y":53.0574}]},{"id":"17", "points":[{"pid":"1", "time":1, "x":37.0000,"y":61.0574},{"pid":"2", "time":1, "x":37.0611,"y":61.0847},{"pid":"3", "time":1, "x":37.2380,"y":61.1614},{"pid":"4", "time":1, "x":37.5215,"y":61.2796},{"pid":"5", "time":1, "x":37.9022,"y":61.4314},{"pid":"6", "time":1, "x":38.3708,"y":61.6089},{"pid":"7", "time":1, "x":38.9178,"y":61.8042},{"pid":"8", "time":1, "x":39.5341,"y":62.0093},{"pid":"9", "time":1, "x":40.2102,"y":62.2164},{"pid":"10", "time":1, "x":40.9368,"y":62.4175},{"pid":"11", "time":1, "x":41.7045,"y":62.6048},{"pid":"12", "time":1, "x":42.5040,"y":62.7703},{"pid":"13", "time":1, "x":43.3260,"y":62.9062},{"pid":"14", "time":1, "x":44.1611,"y":63.0045},{"pid":"15", "time":1, "x":45.0000,"y":63.0574},{"pid":"16", "time":1, "x":45.0000,"y":63.0574},{"pid":"17", "time":1, "x":50.5187,"y":63.2130},{"pid":"18", "time":1, "x":56.0239,"y":63.3226},{"pid":"19", "time":1, "x":61.4524,"y":63.3916},{"pid":"20", "time":1, "x":66.7407,"y":63.4257},{"pid":"21", "time":1, "x":71.8257,"y":63.4303},{"pid":"22", "time":1, "x":76.6441,"y":63.4109},{"pid":"23", "time":1, "x":81.1327,"y":63.3732},{"pid":"24", "time":1, "x":85.2280,"y":63.3226},{"pid":"25", "time":1, "x":88.8669,"y":63.2645},{"pid":"26", "time":1, "x":91.9861,"y":63.2047},{"pid":"27", "time":1, "x":94.5223,"y":63.1485},{"pid":"28", "time":1, "x":96.4122,"y":63.1016},{"pid":"29", "time":1, "x":97.5925,"y":63.0693},{"pid":"30", "time":1, "x":98.0000,"y":63.0574},{"pid":"31", "time":1, "x":98.0000,"y":63.0574},{"pid":"32", "time":1, "x":98.0000,"y":63.0574},{"pid":"33", "time":1, "x":98.0000,"y":63.0574},{"pid":"34", "time":1, "x":98.0000,"y":63.0574},{"pid":"35", "time":1, "x":98.0000,"y":63.0574},{"pid":"36", "time":1, "x":98.0000,"y":63.0574},{"pid":"37", "time":1, "x":98.0000,"y":63.0574},{"pid":"38", "time":1, "x":98.0000,"y":63.0574},{"pid":"39", "time":1, "x":98.0000,"y":63.0574},{"pid":"40", "time":1, "x":98.0000,"y":63.0574},{"pid":"41", "time":1, "x":98.0000,"y":63.0574},{"pid":"42", "time":1, "x":98.0000,"y":63.0574},{"pid":"43", "time":1, "x":98.0000,"y":63.0574},{"pid":"44", "time":1, "x":98.0000,"y":63.0574},{"pid":"45", "time":1, "x":98.0000,"y":63.0574}]},{"id":"18", "points":[{"pid":"1", "time":1, "x":96.0000,"y":62.0574},{"pid":"2", "time":1, "x":95.9535,"y":62.0299},{"pid":"3", "time":1, "x":95.8188,"y":61.9526},{"pid":"4", "time":1, "x":95.6034,"y":61.8337},{"pid":"5", "time":1, "x":95.3145,"y":61.6810},{"pid":"6", "time":1, "x":94.9595,"y":61.5026},{"pid":"7", "time":1, "x":94.5457,"y":61.3065},{"pid":"8", "time":1, "x":94.0805,"y":61.1006},{"pid":"9", "time":1, "x":93.5712,"y":60.8929},{"pid":"10", "time":1, "x":93.0251,"y":60.6915},{"pid":"11", "time":1, "x":92.4496,"y":60.5043},{"pid":"12", "time":1, "x":91.8520,"y":60.3393},{"pid":"13", "time":1, "x":91.2396,"y":60.2045},{"pid":"14", "time":1, "x":90.6199,"y":60.1078},{"pid":"15", "time":1, "x":90.0000,"y":60.0574},{"pid":"16", "time":1, "x":90.0000,"y":60.0574},{"pid":"17", "time":1, "x":85.5058,"y":59.9033},{"pid":"18", "time":1, "x":80.9970,"y":59.7947},{"pid":"19", "time":1, "x":76.5291,"y":59.7263},{"pid":"20", "time":1, "x":72.1579,"y":59.6926},{"pid":"21", "time":1, "x":67.9390,"y":59.6880},{"pid":"22", "time":1, "x":63.9279,"y":59.7072},{"pid":"23", "time":1, "x":60.1804,"y":59.7446},{"pid":"24", "time":1, "x":56.7521,"y":59.7947},{"pid":"25", "time":1, "x":53.6985,"y":59.8522},{"pid":"26", "time":1, "x":51.0754,"y":59.9115},{"pid":"27", "time":1, "x":48.9384,"y":59.9671},{"pid":"28", "time":1, "x":47.3430,"y":60.0136},{"pid":"29", "time":1, "x":46.3450,"y":60.0455},{"pid":"30", "time":1, "x":46.0000,"y":60.0574},{"pid":"31", "time":1, "x":46.0000,"y":60.0574},{"pid":"32", "time":1, "x":46.0000,"y":60.0574},{"pid":"33", "time":1, "x":46.0000,"y":60.0574},{"pid":"34", "time":1, "x":46.0000,"y":60.0574},{"pid":"35", "time":1, "x":46.0000,"y":60.0574},{"pid":"36", "time":1, "x":46.0000,"y":60.0574},{"pid":"37", "time":1, "x":46.0000,"y":60.0574},{"pid":"38", "time":1, "x":46.0000,"y":60.0574},{"pid":"39", "time":1, "x":46.0000,"y":60.0574},{"pid":"40", "time":1, "x":46.0000,"y":60.0574},{"pid":"41", "time":1, "x":46.0000,"y":60.0574},{"pid":"42", "time":1, "x":46.0000,"y":60.0574},{"pid":"43", "time":1, "x":46.0000,"y":60.0574},{"pid":"44", "time":1, "x":46.0000,"y":60.0574},{"pid":"45", "time":1, "x":46.0000,"y":60.0574}]}]}