{"id":"mug_70","strokes":[{"id":"1", "points":[{"pid":"1", "time":1, "x":190.0000,"y":310.5630},{"pid":"2", "time":1, "x":190.1289,"y":310.5916},{"pid":"3", "time":1, "x":190.4996,"y":310.6687},{"pid":"4", "time":1, "x":191.0877,"y":310.7809},{"pid":"5", "time":1, "x":191.8693,"y":310.9152},{"pid":"6", "time":1, "x":192.8200,"y":311.0582},{"pid":"7", "time":1, "x":193.9157,"y":311.1969},{"pid":"8", "time":1, "x":195.1322,"y":311.3180},{"pid":"9", "time":1, "x":196.4454,"y":311.4082},{"pid":"10", "time":1, "x":197.8310,"y":311.4544},{"pid":"11", "time":1, "x":199.2650,"y":311.4434},{"pid":"12", "time":1, "x":200.7230,"y":311.3620},{"pid":"13", "time":1, "x":202.1810,"y":311.1969},{"pid":"14", "time":1, "x":203.6147,"y":310.9350},{"pid":"15", "time":1, "x":205.0000,"y":310.5630},{"pid":"16", "time":1, "x":205.0000,"y":310.5630},{"pid":"17", "time":1, "x":210.1598,"y":308.8205},{"pid":"18", "time":1, "x":214.7016,"y":307.1027},{"pid":"19", "time":1, "x":218.7299,"y":305.4101},{"pid":"20", "time":1, "x":222.3490,"y":303.7430},{"pid":"21", "time":1, "x":225.6634,"y":302.1018},{"pid":"22", "time":1, "x":228.7773,"y":300.4870},{"pid":"23", "time":1, "x":231.7952,"y":298.8988},{"pid":"24", "time":1, "x":234.8215,"y":297.3378},{"pid":"25", "time":1, "x":237.9605,"y":295.8043},{"pid":"26", "time":1, "x":241.3166,"y":294.2987},{"pid":"27", "time":1, "x":244.9942,"y":292.8213},{"pid":"28", "time":1, "x":249.0978,"y":291.3727},{"pid":"29", "time":1, "x":253.7316,"y":289.9531},{"pid":"30", "time":1, "x":259.0000,"y":288.5630},{"pid":"31", "time":1, "x":259.0000,"y":288.5630},{"pid":"32", "time":1, "x":262.5959,"y":287.7143},{"pid":"33", "time":1, "x":265.8101,"y":287.0255},{"pid":"34", "time":1, "x":268.7096,"y":286.4864},{"pid":"35", "time":1, "x":271.3613,"y":286.0871},{"pid":"36", "time":1, "x":273.8324,"y":285.8175},{"pid":"37", "time":1, "x":276.1899,"y":285.6674},{"pid":"38", "time":1, "x":278.5006,"y":285.6269},{"pid":"39", "time":1, "x":280.8318,"y":285.6858},{"pid":"40", "time":1, "x":283.2504,"y":285.8340},{"pid":"41", "time":1, "x":285.8234,"y":286.0616},{"pid":"42", "time":1, "x":288.6178,"y":286.3583},{"pid":"43", "time":1, "x":291.7007,"y":286.7142},{"pid":"44", "time":1, "x":295.1391,"y":287.1191},{"pid":"45", "time":1, "x":299.0000,"y":287.5630},{"pid":"46", "time":1, "x":299.0000,"y":287.5630},{"pid":"47", "time":1, "x":303.8381,"y":288.1222},{"pid":"48", "time":1, "x":308.1007,"y":288.6516},{"pid":"49", "time":1, "x":311.8801,"y":289.1674},{"pid":"50", "time":1, "x":315.2688,"y":289.6858},{"pid":"51", "time":1, "x":318.3592,"y":290.2229},{"pid":"52", "time":1, "x":321.2437,"y":290.7948},{"pid":"53", "time":1, "x":324.0148,"y":291.4178},{"pid":"54", "time":1, "x":326.7649,"y":292.1079},{"pid":"55", "time":1, "x":329.5864,"y":292.8813},{"pid":"56", "time":1, "x":332.5717,"y":293.7541},{"pid":"57", "time":1, "x":335.8133,"y":294.7426},{"pid":"58", "time":1, "x":339.4036,"y":295.8628},{"pid":"59", "time":1, "x":343.4350,"y":297.1309},{"pid":"60", "time":1, "x":348.0000,"y":298.5630},{"pid":"61", "time":1, "x":348.0000,"y":298.5630},{"pid":"62", "time":1, "x":349.5369,"y":299.0745},{"pid":"63", "time":1, "x":350.8668,"y":299.5809},{"pid":"64", "time":1, "x":352.0234,"y":300.0886},{"pid":"65", "time":1, "x":353.0407,"y":300.6038},{"pid":"66", "time":1, "x":353.9525,"y":301.1329},{"pid":"67", "time":1, "x":354.7927,"y":301.6822},{"pid":"68", "time":1, "x":355.5951,"y":302.2580},{"pid":"69", "time":1, "x":356.3937,"y":302.8667},{"pid":"70", "time":1, "x":357.2222,"y":303.5145},{"pid":"71", "time":1, "x":358.1146,"y":304.2079},{"pid":"72", "time":1, "x":359.1047,"y":304.9531},{"pid":"73", "time":1, "x":360.2264,"y":305.7565},{"pid":"74", "time":1, "x":361.5136,"y":306.6243},{"pid":"75", "time":1, "x":363.0000,"y":307.5630},{"pid":"76", "time":1, "x":363.0000,"y":307.5630},{"pid":"77", "time":1, "x":363.3235,"y":307.7539},{"pid":"78", "time":1, "x":363.6353,"y":307.9264},{"pid":"79", "time":1, "x":363.9341,"y":308.0832},{"pid":"80", "time":1, "x":364.2186,"y":308.2271},{"pid":"81", "time":1, "x":364.4876,"y":308.3609},{"pid":"82", "time":1, "x":364.7397,"y":308.4872},{"pid":"83", "time":1, "x":364.9738,"y":308.6089},{"pid":"84", "time":1, "x":365.1885,"y":308.7288},{"pid":"85", "time":1, "x":365.3826,"y":308.8495},{"pid":"86", "time":1, "x":365.5549,"y":308.9739},{"pid":"87", "time":1, "x":365.7040,"y":309.1047},{"pid":"88", "time":1, "x":365.8288,"y":309.2446},{"pid":"89", "time":1, "x":365.9279,"y":309.3965},{"pid":"90", "time":1, "x":366.0000,"y":309.5630},{"pid":"91", "time":1, "x":366.0000,"y":309.5630},{"pid":"92", "time":1, "x":366.1266,"y":310.0099},{"pid":"93", "time":1, "x":366.2344,"y":310.5247},{"pid":"94", "time":1, "x":366.3232,"y":311.0926},{"pid":"95", "time":1, "x":366.3929,"y":311.6985},{"pid":"96", "time":1, "x":366.4433,"y":312.3276},{"pid":"97", "time":1, "x":366.4742,"y":312.9649},{"pid":"98", "time":1, "x":366.4854,"y":313.5953},{"pid":"99", "time":1, "x":366.4769,"y":314.2041},{"pid":"100", "time":1, "x":366.4483,"y":314.7761},{"pid":"101", "time":1, "x":366.3996,"y":315.2966},{"pid":"102", "time":1, "x":366.3306,"y":315.7504},{"pid":"103", "time":1, "x":366.2411,"y":316.1227},{"pid":"104", "time":1, "x":366.1310,"y":316.3986},{"pid":"105", "time":1, "x":366.0000,"y":316.5630},{"pid":"106", "time":1, "x":366.0000,"y":316.5630},{"pid":"107", "time":1, "x":365.4597,"y":316.9272},{"pid":"108", "time":1, "x":364.8283,"y":317.2929},{"pid":"109", "time":1, "x":364.1084,"y":317.6567},{"pid":"110", "time":1, "x":363.3021,"y":318.0152},{"pid":"111", "time":1, "x":362.4117,"y":318.3650},{"pid":"112", "time":1, "x":361.4397,"y":318.7028},{"pid":"113", "time":1, "x":360.3882,"y":319.0250},{"pid":"114", "time":1, "x":359.2597,"y":319.3285},{"pid":"115", "time":1, "x":358.0565,"y":319.6096},{"pid":"116", "time":1, "x":356.7808,"y":319.8651},{"pid":"117", "time":1, "x":355.4350,"y":320.0916},{"pid":"118", "time":1, "x":354.0214,"y":320.2857},{"pid":"119", "time":1, "x":352.5423,"y":320.4440},{"pid":"120", "time":1, "x":351.0000,"y":320.5630},{"pid":"121", "time":1, "x":351.0000,"y":320.5630},{"pid":"122", "time":1, "x":346.2692,"y":320.8673},{"pid":"123", "time":1, "x":342.1202,"y":321.1452},{"pid":"124", "time":1, "x":338.4550,"y":321.3914},{"pid":"125", "time":1, "x":335.1755,"y":321.6010},{"pid":"126", "time":1, "x":332.1834,"y":321.7688},{"pid":"127", "time":1, "x":329.3807,"y":321.8898},{"pid":"128", "time":1, "x":326.6692,"y":321.9589},{"pid":"129", "time":1, "x":323.9508,"y":321.9710},{"pid":"130", "time":1, "x":321.1273,"y":321.9211},{"pid":"131", "time":1, "x":318.1007,"y":321.8041},{"pid":"132", "time":1, "x":314.7728,"y":321.6148},{"pid":"133", "time":1, "x":311.0455,"y":321.3483},{"pid":"134", "time":1, "x":306.8206,"y":320.9994},{"pid":"135", "time":1, "x":302.0000,"y":320.5630},{"pid":"136", "time":1, "x":302.0000,"y":320.5630},{"pid":"137", "time":1, "x":292.4199,"y":319.6002},{"pid":"138", "time":1, "x":282.9245,"y":318.5251},{"pid":"139", "time":1, "x":273.6137,"y":317.3671},{"pid":"140", "time":1, "x":264.5878,"y":316.1555},{"pid":"141", "time":1, "x":255.9467,"y":314.9198},{"pid":"142", "time":1, "x":247.7904,"y":313.6893},{"pid":"143", "time":1, "x":240.2191,"y":312.4936},{"pid":"144", "time":1, "x":233.3326,"y":311.3618},{"pid":"145", "time":1, "x":227.2312,"y":310.3236},{"pid":"146", "time":1, "x":222.0147,"y":309.4082},{"pid":"147", "time":1, "x":217.7833,"y":308.6450},{"pid":"148", "time":1, "x":214.6371,"y":308.0635},{"pid":"149", "time":1, "x":212.6759,"y":307.6930},{"pid":"150", "time":1, "x":212.0000,"y":307.5630},{"pid":"151", "time":1, "x":212.0000,"y":307.5630},{"pid":"152", "time":1, "x":212.0000,"y":307.5630},{"pid":"153", "time":1, "x":212.0000,"y":307.5630},{"pid":"154", "time":1, "x":212.0000,"y":307.5630},{"pid":"155", "time":1, "x":212.0000,"y":307.5630},{"pid":"156", "time":1, "x":212.0000,"y":307.5630},{"pid":"157", "time":1, "x":212.0000,"y":307.5630},{"pid":"158", "time":1, "x":212.0000,"y":307.5630},{"pid":"159", "time":1, "x":212.0000,"y":307.5630},{"pid":"160", "time":1, "x":212.0000,"y":307.5630},{"pid":"161", "time":1, "x":212.0000,"y":307.5630},{"pid":"162", "time":1, "x":212.0000,"y":307.5630},{"pid":"163", "time":1, "x":212.0000,"y":307.5630},{"pid":"164", "time":1, "x":212.0000,"y":307.5630},{"pid":"165", "time":1, "x":212.0000,"y":307.5630}]},{"id":"2", "points":[{"pid":"1", "time":1, "x":208.0000,"y":308.5630},{"pid":"2", "time":1, "x":208.0510,"y":308.5298},{"pid":"3", "time":1, "x":208.1962,"y":308.4325},{"pid":"4", "time":1, "x":208.4237,"y":308.2747},{"pid":"5", "time":1, "x":208.7219,"y":308.0599},{"pid":"6", "time":1, "x":209.0789,"y":307.7918},{"pid":"7", "time":1, "x":209.4831,"y":307.4738},{"pid":"8", "time":1, "x":209.9226,"y":307.1096},{"pid":"9", "time":1, "x":210.3856,"y":306.7026},{"pid":"10", "time":1, "x":210.8605,"y":306.2565},{"pid":"11", "time":1, "x":211.3354,"y":305.7747},{"pid":"12", "time":1, "x":211.7985,"y":305.2610},{"pid":"13", "time":1, "x":212.2382,"y":304.7187},{"pid":"14", "time":1, "x":212.6426,"y":304.1515},{"pid":"15", "time":1, "x":213.0000,"y":303.5630},{"pid":"16", "time":1, "x":213.0000,"y":303.5630},{"pid":"17", "time":1, "x":214.2383,"y":301.3800},{"pid":"18", "time":1, "x":215.3974,"y":299.4383},{"pid":"19", "time":1, "x":216.4796,"y":297.6956},{"pid":"20", "time":1, "x":217.4874,"y":296.1095},{"pid":"21", "time":1, "x":218.4232,"y":294.6379},{"pid":"22", "time":1, "x":219.2893,"y":293.2384},{"pid":"23", "time":1, "x":220.0882,"y":291.8686},{"pid":"24", "time":1, "x":220.8223,"y":290.4864},{"pid":"25", "time":1, "x":221.4939,"y":289.0495},{"pid":"26", "time":1, "x":222.1056,"y":287.5155},{"pid":"27", "time":1, "x":222.6596,"y":285.8421},{"pid":"28", "time":1, "x":223.1584,"y":283.9871},{"pid":"29", "time":1, "x":223.6044,"y":281.9082},{"pid":"30", "time":1, "x":224.0000,"y":279.5630},{"pid":"31", "time":1, "x":224.0000,"y":279.5630},{"pid":"32", "time":1, "x":224.9174,"y":273.1349},{"pid":"33", "time":1, "x":225.6435,"y":267.4584},{"pid":"34", "time":1, "x":226.1992,"y":262.4006},{"pid":"35", "time":1, "x":226.6051,"y":257.8284},{"pid":"36", "time":1, "x":226.8821,"y":253.6090},{"pid":"37", "time":1, "x":227.0510,"y":249.6093},{"pid":"38", "time":1, "x":227.1324,"y":245.6963},{"pid":"39", "time":1, "x":227.1472,"y":241.7370},{"pid":"40", "time":1, "x":227.1161,"y":237.5985},{"pid":"41", "time":1, "x":227.0600,"y":233.1478},{"pid":"42", "time":1, "x":226.9995,"y":228.2518},{"pid":"43", "time":1, "x":226.9555,"y":222.7777},{"pid":"44", "time":1, "x":226.9488,"y":216.5924},{"pid":"45", "time":1, "x":227.0000,"y":209.5630},{"pid":"46", "time":1, "x":227.0000,"y":209.5630},{"pid":"47", "time":1, "x":227.1531,"y":190.5527},{"pid":"48", "time":1, "x":227.1644,"y":173.5701},{"pid":"49", "time":1, "x":227.0632,"y":158.3231},{"pid":"50", "time":1, "x":226.8794,"y":144.5193},{"pid":"51", "time":1, "x":226.6423,"y":131.8665},{"pid":"52", "time":1, "x":226.3817,"y":120.0725},{"pid":"53", "time":1, "x":226.1272,"y":108.8449},{"pid":"54", "time":1, "x":225.9083,"y":97.8915},{"pid":"55", "time":1, "x":225.7545,"y":86.9201},{"pid":"56", "time":1, "x":225.6956,"y":75.6384},{"pid":"57", "time":1, "x":225.7611,"y":63.7541},{"pid":"58", "time":1, "x":225.9806,"y":50.9749},{"pid":"59", "time":1, "x":226.3837,"y":37.0086},{"pid":"60", "time":1, "x":227.0000,"y":21.5630},{"pid":"61", "time":1, "x":227.0000,"y":21.5630},{"pid":"62", "time":1, "x":227.1006,"y":20.5195},{"pid":"63", "time":1, "x":227.3026,"y":19.5332},{"pid":"64", "time":1, "x":227.6015,"y":18.5968},{"pid":"65", "time":1, "x":227.9929,"y":17.7033},{"pid":"66", "time":1, "x":228.4722,"y":16.8456},{"pid":"67", "time":1, "x":229.0350,"y":16.0166},{"pid":"68", "time":1, "x":229.6766,"y":15.2092},{"pid":"69", "time":1, "x":230.3927,"y":14.4161},{"pid":"70", "time":1, "x":231.1787,"y":13.6304},{"pid":"71", "time":1, "x":232.0302,"y":12.8450},{"pid":"72", "time":1, "x":232.9425,"y":12.0526},{"pid":"73", "time":1, "x":233.9113,"y":11.2462},{"pid":"74", "time":1, "x":234.9319,"y":10.4187},{"pid":"75", "time":1, "x":236.0000,"y":9.5630},{"pid":"76", "time":1, "x":236.0000,"y":9.5630},{"pid":"77", "time":1, "x":237.2615,"y":8.5456},{"pid":"78", "time":1, "x":238.4322,"y":7.5947},{"pid":"79", "time":1, "x":239.5302,"y":6.7107},{"pid":"80", "time":1, "x":240.5737,"y":5.8942},{"pid":"81", "time":1, "x":241.5807,"y":5.1458},{"pid":"82", "time":1, "x":242.5695,"y":4.4660},{"pid":"83", "time":1, "x":243.5582,"y":3.8553},{"pid":"84", "time":1, "x":244.5649,"y":3.3143},{"pid":"85", "time":1, "x":245.6078,"y":2.8436},{"pid":"86", "time":1, "x":246.7050,"y":2.4437},{"pid":"87", "time":1, "x":247.8747,"y":2.1151},{"pid":"88", "time":1, "x":249.1350,"y":1.8585},{"pid":"89", "time":1, "x":250.5041,"y":1.6742},{"pid":"90", "time":1, "x":252.0000,"y":1.5630},{"pid":"91", "time":1, "x":252.0000,"y":1.5630},{"pid":"92", "time":1, "x":263.8631,"y":1.0281},{"pid":"93", "time":1, "x":274.5546,"y":0.6112},{"pid":"94", "time":1, "x":284.2711,"y":0.3062},{"pid":"95", "time":1, "x":293.2089,"y":0.1067},{"pid":"96", "time":1, "x":301.5648,"y":0.0067},{"pid":"97", "time":1, "x":309.5351,"y":0.0000},{"pid":"98", "time":1, "x":317.3163,"y":0.0804},{"pid":"99", "time":1, "x":325.1051,"y":0.2417},{"pid":"100", "time":1, "x":333.0979,"y":0.4777},{"pid":"101", "time":1, "x":341.4912,"y":0.7824},{"pid":"102", "time":1, "x":350.4815,"y":1.1494},{"pid":"103", "time":1, "x":360.2654,"y":1.5726},{"pid":"104", "time":1, "x":371.0394,"y":2.0459},{"pid":"105", "time":1, "x":383.0000,"y":2.5630},{"pid":"106", "time":1, "x":383.0000,"y":2.5630},{"pid":"107", "time":1, "x":383.9460,"y":2.6316},{"pid":"108", "time":1, "x":384.8228,"y":2.7523},{"pid":"109", "time":1, "x":385.6387,"y":2.9233},{"pid":"110", "time":1, "x":386.4021,"y":3.1425},{"pid":"111", "time":1, "x":387.1214,"y":3.4081},{"pid":"112", "time":1, "x":387.8051,"y":3.7181},{"pid":"113", "time":1, "x":388.4616,"y":4.0705},{"pid":"114", "time":1, "x":389.0992,"y":4.4634},{"pid":"115", "time":1, "x":389.7264,"y":4.8949},{"pid":"116", "time":1, "x":390.3515,"y":5.3631},{"pid":"117", "time":1, "x":390.9830,"y":5.8659},{"pid":"118", "time":1, "x":391.6294,"y":6.4014},{"pid":"119", "time":1, "x":392.2989,"y":6.9678},{"pid":"120", "time":1, "x":393.0000,"y":7.5630},{"pid":"121", "time":1, "x":393.0000,"y":7.5630},{"pid":"122", "time":1, "x":393.3912,"y":7.9076},{"pid":"123", "time":1, "x":393.7489,"y":8.2522},{"pid":"124", "time":1, "x":394.0745,"y":8.6001},{"pid":"125", "time":1, "x":394.3699,"y":8.9544},{"pid":"126", "time":1, "x":394.6364,"y":9.3185},{"pid":"127", "time":1, "x":394.8757,"y":9.6954},{"pid":"128", "time":1, "x":395.0893,"y":10.0885},{"pid":"129", "time":1, "x":395.2790,"y":10.5010},{"pid":"130", "time":1, "x":395.4461,"y":10.9361},{"pid":"131", "time":1, "x":395.5923,"y":11.3969},{"pid":"132", "time":1, "x":395.7193,"y":11.8868},{"pid":"133", "time":1, "x":395.8285,"y":12.4090},{"pid":"134", "time":1, "x":395.9215,"y":12.9667},{"pid":"135", "time":1, "x":396.0000,"y":13.5630},{"pid":"136", "time":1, "x":396.0000,"y":13.5630},{"pid":"137", "time":1, "x":396.4243,"y":16.9788},{"pid":"138", "time":1, "x":396.8488,"y":20.0326},{"pid":"139", "time":1, "x":397.2626,"y":22.7852},{"pid":"140", "time":1, "x":397.6549,"y":25.2974},{"pid":"141", "time":1, "x":398.0148,"y":27.6298},{"pid":"142", "time":1, "x":398.3314,"y":29.8434},{"pid":"143", "time":1, "x":398.5938,"y":31.9988},{"pid":"144", "time":1, "x":398.7911,"y":34.1568},{"pid":"145", "time":1, "x":398.9125,"y":36.3782},{"pid":"146", "time":1, "x":398.9471,"y":38.7238},{"pid":"147", "time":1, "x":398.8840,"y":41.2543},{"pid":"148", "time":1, "x":398.7124,"y":44.0305},{"pid":"149", "time":1, "x":398.4214,"y":47.1131},{"pid":"150", "time":1, "x":398.0000,"y":50.5630},{"pid":"151", "time":1, "x":398.0000,"y":50.5630},{"pid":"152", "time":1, "x":397.3505,"y":54.9062},{"pid":"153", "time":1, "x":396.6508,"y":58.6991},{"pid":"154", "time":1, "x":395.9026,"y":62.0358},{"pid":"155", "time":1, "x":395.1079,"y":65.0106},{"pid":"156", "time":1, "x":394.2683,"y":67.7176},{"pid":"157", "time":1, "x":393.3859,"y":70.2509},{"pid":"158", "time":1, "x":392.4623,"y":72.7046},{"pid":"159", "time":1, "x":391.4994,"y":75.1730},{"pid":"160", "time":1, "x":390.4991,"y":77.7502},{"pid":"161", "time":1, "x":389.4632,"y":80.5303},{"pid":"162", "time":1, "x":388.3935,"y":83.6075},{"pid":"163", "time":1, "x":387.2919,"y":87.0759},{"pid":"164", "time":1, "x":386.1601,"y":91.0297},{"pid":"165", "time":1, "x":385.0000,"y":95.5630},{"pid":"166", "time":1, "x":385.0000,"y":95.5630},{"pid":"167", "time":1, "x":383.8701,"y":100.0992},{"pid":"168", "time":1, "x":382.8274,"y":104.0567},{"pid":"169", "time":1, "x":381.8687,"y":107.5320},{"pid":"170", "time":1, "x":380.9910,"y":110.6217},{"pid":"171", "time":1, "x":380.1912,"y":113.4224},{"pid":"172", "time":1, "x":379.4664,"y":116.0307},{"pid":"173", "time":1, "x":378.8135,"y":118.5432},{"pid":"174", "time":1, "x":378.2294,"y":121.0565},{"pid":"175", "time":1, "x":377.7111,"y":123.6673},{"pid":"176", "time":1, "x":377.2555,"y":126.4720},{"pid":"177", "time":1, "x":376.8597,"y":129.5674},{"pid":"178", "time":1, "x":376.5205,"y":133.0499},{"pid":"179", "time":1, "x":376.2350,"y":137.0163},{"pid":"180", "time":1, "x":376.0000,"y":141.5630},{"pid":"181", "time":1, "x":376.0000,"y":141.5630},{"pid":"182", "time":1, "x":375.4096,"y":157.7496},{"pid":"183", "time":1, "x":375.0814,"y":172.4337},{"pid":"184", "time":1, "x":374.9726,"y":185.8134},{"pid":"185", "time":1, "x":375.0403,"y":198.0869},{"pid":"186", "time":1, "x":375.2416,"y":209.4523},{"pid":"187", "time":1, "x":375.5338,"y":220.1076},{"pid":"188", "time":1, "x":375.8740,"y":230.2511},{"pid":"189", "time":1, "x":376.2193,"y":240.0807},{"pid":"190", "time":1, "x":376.5269,"y":249.7946},{"pid":"191", "time":1, "x":376.7539,"y":259.5910},{"pid":"192", "time":1, "x":376.8576,"y":269.6679},{"pid":"193", "time":1, "x":376.7951,"y":280.2235},{"pid":"194", "time":1, "x":376.5235,"y":291.4558},{"pid":"195", "time":1, "x":376.0000,"y":303.5630},{"pid":"196", "time":1, "x":376.0000,"y":303.5630},{"pid":"197", "time":1, "x":375.8353,"y":304.3301},{"pid":"198", "time":1, "x":375.4444,"y":305.1452},{"pid":"199", "time":1, "x":374.8654,"y":305.9915},{"pid":"200", "time":1, "x":374.1365,"y":306.8523},{"pid":"201", "time":1, "x":373.2959,"y":307.7108},{"pid":"202", "time":1, "x":372.3817,"y":308.5501},{"pid":"203", "time":1, "x":371.4321,"y":309.3536},{"pid":"204", "time":1, "x":370.4853,"y":310.1044},{"pid":"205", "time":1, "x":369.5794,"y":310.7857},{"pid":"206", "time":1, "x":368.7526,"y":311.3808},{"pid":"207", "time":1, "x":368.0431,"y":311.8728},{"pid":"208", "time":1, "x":367.4890,"y":312.2451},{"pid":"209", "time":1, "x":367.1286,"y":312.4807},{"pid":"210", "time":1, "x":367.0000,"y":312.5630},{"pid":"211", "time":1, "x":367.0000,"y":312.5630},{"pid":"212", "time":1, "x":367.0000,"y":312.5630},{"pid":"213", "time":1, "x":367.0000,"y":312.5630},{"pid":"214", "time":1, "x":367.0000,"y":312.5630},{"pid":"215", "time":1, "x":367.0000,"y":312.5630},{"pid":"216", "time":1, "x":367.0000,"y":312.5630},{"pid":"217", "time":1, "x":367.0000,"y":312.5630},{"pid":"218", "time":1, "x":367.0000,"y":312.5630},{"pid":"219", "time":1, "x":367.0000,"y":312.5630},{"pid":"220", "time":1, "x":367.0000,"y":312.5630},{"pid":"221", "time":1, "x":367.0000,"y":312.5630},{"pid":"222", "time":1, "x":367.0000,"y":312.5630},{"pid":"223", "time":1, "x":367.0000,"y":312.5630},{"pid":"224", "time":1, "x":367.0000,"y":312.5630},{"pid":"225", "time":1, "x":367.0000,"y":312.5630}]},{"id":"3", "points":[{"pid":"1", "time":1, "x":378.0000,"y":286.5630},{"pid":"2", "time":1, "x":377.9707,"y":286.5340},{"pid":"3", "time":1, "x":377.8886,"y":286.4528},{"pid":"4", "time":1, "x":377.7625,"y":286.3280},{"pid":"5", "time":1, "x":377.6013,"y":286.1684},{"pid":"6", "time":1, "x":377.4139,"y":285.9825},{"pid":"7", "time":1, "x":377.2089,"y":285.7792},{"pid":"8", "time":1, "x":376.9954,"y":285.5670},{"pid":"9", "time":1, "x":376.7820,"y":285.3546},{"pid":"10", "time":1, "x":376.5776,"y":285.1508},{"pid":"11", "time":1, "x":376.3911,"y":284.9641},{"pid":"12", "time":1, "x":376.2312,"y":284.8034},{"pid":"13", "time":1, "x":376.1069,"y":284.6771},{"pid":"14", "time":1, "x":376.0269,"y":284.5941},{"pid":"15", "time":1, "x":376.0000,"y":284.5630},{"pid":"16", "time":1, "x":376.0000,"y":284.5630},{"pid":"17", "time":1, "x":376.3423,"y":284.3332},{"pid":"18", "time":1, "x":376.8981,"y":284.0339},{"pid":"19", "time":1, "x":377.6449,"y":283.6638},{"pid":"20", "time":1, "x":378.5601,"y":283.2217},{"pid":"21", "time":1, "x":379.6210,"y":282.7062},{"pid":"22", "time":1, "x":380.8051,"y":282.1163},{"pid":"23", "time":1, "x":382.0898,"y":281.4505},{"pid":"24", "time":1, "x":383.4525,"y":280.7077},{"pid":"25", "time":1, "x":384.8705,"y":279.8866},{"pid":"26", "time":1, "x":386.3212,"y":278.9859},{"pid":"27", "time":1, "x":387.7822,"y":278.0045},{"pid":"28", "time":1, "x":389.2307,"y":276.9410},{"pid":"29", "time":1, "x":390.6442,"y":275.7943},{"pid":"30", "time":1, "x":392.0000,"y":274.5630},{"pid":"31", "time":1, "x":392.0000,"y":274.5630},{"pid":"32", "time":1, "x":393.4651,"y":273.1329},{"pid":"33", "time":1, "x":394.7514,"y":271.8406},{"pid":"34", "time":1, "x":395.8830,"y":270.6572},{"pid":"35", "time":1, "x":396.8839,"y":269.5537},{"pid":"36", "time":1, "x":397.7783,"y":268.5014},{"pid":"37", "time":1, "x":398.5902,"y":267.4712},{"pid":"38", "time":1, "x":399.3435,"y":266.4344},{"pid":"39", "time":1, "x":400.0625,"y":265.3620},{"pid":"40", "time":1, "x":400.7710,"y":264.2251},{"pid":"41", "time":1, "x":401.4932,"y":262.9949},{"pid":"42", "time":1, "x":402.2532,"y":261.6425},{"pid":"43", "time":1, "x":403.0750,"y":260.1390},{"pid":"44", "time":1, "x":403.9825,"y":258.4554},{"pid":"45", "time":1, "x":405.0000,"y":256.5630},{"pid":"46", "time":1, "x":405.0000,"y":256.5630},{"pid":"47", "time":1, "x":406.0383,"y":254.6498},{"pid":"48", "time":1, "x":406.9713,"y":252.9480},{"pid":"49", "time":1, "x":407.8074,"y":251.4207},{"pid":"50", "time":1, "x":408.5550,"y":250.0308},{"pid":"51", "time":1, "x":409.2223,"y":248.7414},{"pid":"52", "time":1, "x":409.8178,"y":247.5156},{"pid":"53", "time":1, "x":410.3499,"y":246.3165},{"pid":"54", "time":1, "x":410.8268,"y":245.1070},{"pid":"55", "time":1, "x":411.2571,"y":243.8501},{"pid":"56", "time":1, "x":411.6489,"y":242.5091},{"pid":"57", "time":1, "x":412.0108,"y":241.0468},{"pid":"58", "time":1, "x":412.3510,"y":239.4263},{"pid":"59", "time":1, "x":412.6780,"y":237.6107},{"pid":"60", "time":1, "x":413.0000,"y":235.5630},{"pid":"61", "time":1, "x":413.0000,"y":235.5630},{"pid":"62", "time":1, "x":413.4132,"y":232.2933},{"pid":"63", "time":1, "x":413.7037,"y":228.9874},{"pid":"64", "time":1, "x":413.8863,"y":225.6894},{"pid":"65", "time":1, "x":413.9757,"y":222.4435},{"pid":"66", "time":1, "x":413.9867,"y":219.2938},{"pid":"67", "time":1, "x":413.9342,"y":216.2845},{"pid":"68", "time":1, "x":413.8328,"y":213.4598},{"pid":"69", "time":1, "x":413.6975,"y":210.8637},{"pid":"70", "time":1, "x":413.5430,"y":208.5406},{"pid":"71", "time":1, "x":413.3841,"y":206.5344},{"pid":"72", "time":1, "x":413.2355,"y":204.8894},{"pid":"73", "time":1, "x":413.1121,"y":203.6497},{"pid":"74", "time":1, "x":413.0287,"y":202.8595},{"pid":"75", "time":1, "x":413.0000,"y":202.5630},{"pid":"76", "time":1, "x":413.0000,"y":202.5630},{"pid":"77", "time":1, "x":413.0429,"y":202.5941},{"pid":"78", "time":1, "x":413.1623,"y":202.6908},{"pid":"79", "time":1, "x":413.3457,"y":202.8465},{"pid":"80", "time":1, "x":413.5807,"y":203.0546},{"pid":"81", "time":1, "x":413.8545,"y":203.3085},{"pid":"82", "time":1, "x":414.1547,"y":203.6015},{"pid":"83", "time":1, "x":414.4687,"y":203.9271},{"pid":"84", "time":1, "x":414.7840,"y":204.2787},{"pid":"85", "time":1, "x":415.0881,"y":204.6496},{"pid":"86", "time":1, "x":415.3683,"y":205.0332},{"pid":"87", "time":1, "x":415.6121,"y":205.4230},{"pid":"88", "time":1, "x":415.8071,"y":205.8123},{"pid":"89", "time":1, "x":415.9405,"y":206.1945},{"pid":"90", "time":1, "x":416.0000,"y":206.5630},{"pid":"91", "time":1, "x":416.0000,"y":206.5630},{"pid":"92", "time":1, "x":416.2206,"y":211.1196},{"pid":"93", "time":1, "x":416.3995,"y":215.3120},{"pid":"94", "time":1, "x":416.5388,"y":219.2071},{"pid":"95", "time":1, "x":416.6402,"y":222.8719},{"pid":"96", "time":1, "x":416.7057,"y":226.3731},{"pid":"97", "time":1, "x":416.7373,"y":229.7778},{"pid":"98", "time":1, "x":416.7369,"y":233.1527},{"pid":"99", "time":1, "x":416.7064,"y":236.5648},{"pid":"100", "time":1, "x":416.6478,"y":240.0809},{"pid":"101", "time":1, "x":416.5630,"y":243.7679},{"pid":"102", "time":1, "x":416.4538,"y":247.6928},{"pid":"103", "time":1, "x":416.3223,"y":251.9223},{"pid":"104", "time":1, "x":416.1704,"y":256.5234},{"pid":"105", "time":1, "x":416.0000,"y":261.5630},{"pid":"106", "time":1, "x":416.0000,"y":261.5630},{"pid":"107", "time":1, "x":415.9759,"y":261.9313},{"pid":"108", "time":1, "x":415.9305,"y":262.2597},{"pid":"109", "time":1, "x":415.8647,"y":262.5549},{"pid":"110", "time":1, "x":415.7791,"y":262.8238},{"pid":"111", "time":1, "x":415.6745,"y":263.0732},{"pid":"112", "time":1, "x":415.5516,"y":263.3099},{"pid":"113", "time":1, "x":415.4112,"y":263.5406},{"pid":"114", "time":1, "x":415.2540,"y":263.7723},{"pid":"115", "time":1, "x":415.0808,"y":264.0117},{"pid":"116", "time":1, "x":414.8923,"y":264.2656},{"pid":"117", "time":1, "x":414.6892,"y":264.5409},{"pid":"118", "time":1, "x":414.4723,"y":264.8444},{"pid":"119", "time":1, "x":414.2423,"y":265.1828},{"pid":"120", "time":1, "x":414.0000,"y":265.5630},{"pid":"121", "time":1, "x":414.0000,"y":265.5630},{"pid":"122", "time":1, "x":413.4439,"y":266.4853},{"pid":"123", "time":1, "x":412.9698,"y":267.3047},{"pid":"124", "time":1, "x":412.5622,"y":268.0361},{"pid":"125", "time":1, "x":412.2054,"y":268.6946},{"pid":"126", "time":1, "x":411.8837,"y":269.2952},{"pid":"127", "time":1, "x":411.5818,"y":269.8527},{"pid":"128", "time":1, "x":411.2838,"y":270.3822},{"pid":"129", "time":1, "x":410.9743,"y":270.8987},{"pid":"130", "time":1, "x":410.6375,"y":271.4171},{"pid":"131", "time":1, "x":410.2580,"y":271.9525},{"pid":"132", "time":1, "x":409.8201,"y":272.5198},{"pid":"133", "time":1, "x":409.3082,"y":273.1340},{"pid":"134", "time":1, "x":408.7067,"y":273.8101},{"pid":"135", "time":1, "x":408.0000,"y":274.5630},{"pid":"136", "time":1, "x":408.0000,"y":274.5630},{"pid":"137", "time":1, "x":406.3837,"y":276.2636},{"pid":"138", "time":1, "x":404.9588,"y":277.7890},{"pid":"139", "time":1, "x":403.6901,"y":279.1618},{"pid":"140", "time":1, "x":402.5425,"y":280.4040},{"pid":"141", "time":1, "x":401.4809,"y":281.5382},{"pid":"142", "time":1, "x":400.4702,"y":282.5865},{"pid":"143", "time":1, "x":399.4752,"y":283.5714},{"pid":"144", "time":1, "x":398.4609,"y":284.5151},{"pid":"145", "time":1, "x":397.3920,"y":285.4400},{"pid":"146", "time":1, "x":396.2334,"y":286.3683},{"pid":"147", "time":1, "x":394.9501,"y":287.3225},{"pid":"148", "time":1, "x":393.5068,"y":288.3248},{"pid":"149", "time":1, "x":391.8685,"y":289.3975},{"pid":"150", "time":1, "x":390.0000,"y":290.5630},{"pid":"151", "time":1, "x":390.0000,"y":290.5630},{"pid":"152", "time":1, "x":388.3957,"y":291.4705},{"pid":"153", "time":1, "x":386.7161,"y":292.2929},{"pid":"154", "time":1, "x":384.9923,"y":293.0329},{"pid":"155", "time":1, "x":383.2553,"y":293.6935},{"pid":"156", "time":1, "x":381.5363,"y":294.2775},{"pid":"157", "time":1, "x":379.8663,"y":294.7879},{"pid":"158", "time":1, "x":378.2764,"y":295.2274},{"pid":"159", "time":1, "x":376.7977,"y":295.5990},{"pid":"160", "time":1, "x":375.4612,"y":295.9055},{"pid":"161", "time":1, "x":374.2981,"y":296.1499},{"pid":"162", "time":1, "x":373.3393,"y":296.3349},{"pid":"163", "time":1, "x":372.6159,"y":296.4636},{"pid":"164", "time":1, "x":372.1592,"y":296.5386},{"pid":"165", "time":1, "x":372.0000,"y":296.5630},{"pid":"166", "time":1, "x":372.0000,"y":296.5630},{"pid":"167", "time":1, "x":372.0000,"y":296.5630},{"pid":"168", "time":1, "x":372.0000,"y":296.5630},{"pid":"169", "time":1, "x":372.0000,"y":296.5630},{"pid":"170", "time":1, "x":372.0000,"y":296.5630},{"pid":"171", "time":1, "x":372.0000,"y":296.5630},{"pid":"172", "time":1, "x":372.0000,"y":296.5630},{"pid":"173", "time":1, "x":372.0000,"y":296.5630},{"pid":"174", "time":1, "x":372.0000,"y":296.5630},{"pid":"175", "time":1, "x":372.0000,"y":296.5630},{"pid":"176", "time":1, "x":372.0000,"y":296.5630},{"pid":"177", "time":1, "x":372.0000,"y":296.5630},{"pid":"178", "time":1, "x":372.0000,"y":296.5630},{"pid":"179", "time":1, "x":372.0000,"y":296.5630},{"pid":"180", "time":1, "x":372.0000,"y":296.5630}]}]}